{"indicator":{"name":"Término de facturación de energía activa del PVPC 2.0TD","short_name":"PVPC T. 2.0TD","id":1001,"composited":false,"step_type":"linear","disaggregated":true,"magnitud":[{"name":"Precio","id":23}],"tiempo":[{"name":"Hora","id":4}],"geos":[{"geo_id":8741,"geo_name":"Península"},{"geo_id":8742,"geo_name":"Canarias"},{"geo_id":8743,"geo_name":"Baleares"},{"geo_id":8744,"geo_name":"Ceuta"},{"geo_id":8745,"geo_name":"Melilla"}],"values_updated_at":"2022-09-18T20:17:27.000+02:00","values":[{"value":323.31,"datetime":"2022-09-19T00:00:00.000+02:00","datetime_utc":"2022-09-18T22:00:00Z","tz_time":"2022-09-18T22:00:00.000Z","geo_id":8741,"geo_name":"Península"},{"value":323.31,"datetime":"2022-09-19T00:00:00.000+02:00","datetime_utc":"2022-09-18T22:00:00Z","tz_time":"2022-09-18T22:00:00.000Z","geo_id":8742,"geo_name":"Canarias"},{"value":323.31,"datetime":"2022-09-19T00:00:00.000+02:00","datetime_utc":"2022-09-18T22:00:00Z","tz_time":"2022-09-18T22:00:00.000Z","geo_id":8743,"geo_name":"Baleares"},{"value":323.31,"datetime":"2022-09-19T00:00:00.000+02:00","datetime_utc":"2022-09-18T22:00:00Z","tz_time":"2022-09-18T22:00:00.000Z","geo_id":8744,"geo_name":"Ceuta"},{"value":323.31,"datetime":"2022-09-19T00:00:00.000+02:00","datetime_utc":"2022-09-18T22:00:00Z","tz_time":"2022-09-18T22:00:00.000Z","geo_id":8745,"geo_name":"Melilla"},{"value":303.04,"datetime":"2022-09-19T01:00:00.000+02:00","datetime_utc":"2022-09-18T23:00:00Z","tz_time":"2022-09-18T23:00:00.000Z","geo_id":8741,"geo_name":"Península"},{"value":303.04,"datetime":"2022-09-19T01:00:00.000+02:00","datetime_utc":"2022-09-18T23:00:00Z","tz_time":"2022-09-18T23:00:00.000Z","geo_id":8742,"geo_name":"Canarias"},{"value":303.04,"datetime":"2022-09-19T01:00:00.000+02:00","datetime_utc":"2022-09-18T23:00:00Z","tz_time":"2022-09-18T23:00:00.000Z","geo_id":8743,"geo_name":"Baleares"},{"value":303.04,"datetime":"2022-09-19T01:00:00.000+02:00","datetime_utc":"2022-09-18T23:00:00Z","tz_time":"2022-09-18T23:00:00.000Z","geo_id":8744,"geo_name":"Ceuta"},{"value":303.04,"datetime":"2022-09-19T01:00:00.000+02:00","datetime_utc":"2022-09-18T23:00:00Z","tz_time":"2022-09-18T23:00:00.000Z","geo_id":8745,"geo_name":"Melilla"},{"value":300.54,"datetime":"2022-09-19T02:00:00.000+02:00","datetime_utc":"2022-09-19T00:00:00Z","tz_time":"2022-09-19T00:00:00.000Z","geo_id":8741,"geo_name":"Península"},{"value":300.54,"datetime":"2022-09-19T02:00:00.000+02:00","datetime_utc":"2022-09-19T00:00:00Z","tz_time":"2022-09-19T00:00:00.000Z","geo_id":8742,"geo_name":"Canarias"},{"value":300.54,"datetime":"2022-09-19T02:00:00.000+02:00","datetime_utc":"2022-09-19T00:00:00Z","tz_time":"2022-09-19T00:00:00.000Z","geo_id":8743,"geo_name":"Baleares"},{"value":300.54,"datetime":"2022-09-19T02:00:00.000+02:00","datetime_utc":"2022-09-19T00:00:00Z","tz_time":"2022-09-19T00:00:00.000Z","geo_id":8744,"geo_name":"Ceuta"},{"value":300.54,"datetime":"2022-09-19T02:00:00.000+02:00","datetime_utc":"2022-09-19T00:00:00Z","tz_time":"2022-09-19T00:00:00.000Z","geo_id":8745,"geo_name":"Melilla"},{"value":301.21,"datetime":"2022-09-19T03:00:00.000+02:00","datetime_utc":"2022-09-19T01:00:00Z","tz_time":"2022-09-19T01:00:00.000Z","geo_id":8741,"geo_name":"Península"},{"value":301.21,"datetime":"2022-09-19T03:00:00.000+02:00","datetime_utc":"2022-09-19T01:00:00Z","tz_time":"2022-09-19T01:00:00.000Z","geo_id":8742,"geo_name":"Canarias"},{"value":301.21,"datetime":"2022-09-19T03:00:00.000+02:00","datetime_utc":"2022-09-19T01:00:00Z","tz_time":"2022-09-19T01:00:00.000Z","geo_id":8743,"geo_name":"Baleares"},{"value":301.21,"datetime":"2022-09-19T03:00:00.000+02:00","datetime_utc":"2022-09-19T01:00:00Z","tz_time":"2022-09-19T01:00:00.000Z","geo_id":8744,"geo_name":"Ceuta"},{"value":301.21,"datetime":"2022-09-19T03:00:00.000+02:00","datetime_utc":"2022-09-19T01:00:00Z","tz_time":"2022-09-19T01:00:00.000Z","geo_id":8745,"geo_name":"Melilla"},{"value":316.53,"datetime":"2022-09-19T04:00:00.000+02:00","datetime_utc":"2022-09-19T02:00:00Z","tz_time":"2022-09-19T02:00:00.000Z","geo_id":8741,"geo_name":"Península"},{"value":316.53,"datetime":"2022-09-19T04:00:00.000+02:00","datetime_utc":"2022-09-19T02:00:00Z","tz_time":"2022-09-19T02:00:00.000Z","geo_id":8742,"geo_name":"Canarias"},{"value":316.53,"datetime":"2022-09-19T04:00:00.000+02:00","datetime_utc":"2022-09-19T02:00:00Z","tz_time":"2022-09-19T02:00:00.000Z","geo_id":8743,"geo_name":"Baleares"},{"value":316.53,"datetime":"2022-09-19T04:00:00.000+02:00","datetime_utc":"2022-09-19T02:00:00Z","tz_time":"2022-09-19T02:00:00.000Z","geo_id":8744,"geo_name":"Ceuta"},{"value":316.53,"datetime":"2022-09-19T04:00:00.000+02:00","datetime_utc":"2022-09-19T02:00:00Z","tz_time":"2022-09-19T02:00:00.000Z","geo_id":8745,"geo_name":"Melilla"},{"value":323.14,"datetime":"2022-09-19T05:00:00.000+02:00","datetime_utc":"2022-09-19T03:00:00Z","tz_time":"2022-09-19T03:00:00.000Z","geo_id":8741,"geo_name":"Península"},{"value":323.14,"datetime":"2022-09-19T05:00:00.000+02:00","datetime_utc":"2022-09-19T03:00:00Z","tz_time":"2022-09-19T03:00:00.000Z","geo_id":8742,"geo_name":"Canarias"},{"value":323.14,"datetime":"2022-09-19T05:00:00.000+02:00","datetime_utc":"2022-09-19T03:00:00Z","tz_time":"2022-09-19T03:00:00.000Z","geo_id":8743,"geo_name":"Baleares"},{"value":323.14,"datetime":"2022-09-19T05:00:00.000+02:00","datetime_utc":"2022-09-19T03:00:00Z","tz_time":"2022-09-19T03:00:00.000Z","geo_id":8744,"geo_name":"Ceuta"},{"value":323.14,"datetime":"2022-09-19T05:00:00.000+02:00","datetime_utc":"2022-09-19T03:00:00Z","tz_time":"2022-09-19T03:00:00.000Z","geo_id":8745,"geo_name":"Melilla"},{"value":334.77,"datetime":"2022-09-19T06:00:00.000+02:00","datetime_utc":"2022-09-19T04:00:00Z","tz_time":"2022-09-19T04:00:00.000Z","geo_id":8741,"geo_name":"Península"},{"value":334.77,"datetime":"2022-09-19T06:00:00.000+02:00","datetime_utc":"2022-09-19T04:00:00Z","tz_time":"2022-09-19T04:00:00.000Z","geo_id":8742,"geo_name":"Canarias"},{"value":334.77,"datetime":"2022-09-19T06:00:00.000+02:00","datetime_utc":"2022-09-19T04:00:00Z","tz_time":"2022-09-19T04:00:00.000Z","geo_id":8743,"geo_name":"Baleares"},{"value":334.77,"datetime":"2022-09-19T06:00:00.000+02:00","datetime_utc":"2022-09-19T04:00:00Z","tz_time":"2022-09-19T04:00:00.000Z","geo_id":8744,"geo_name":"Ceuta"},{"value":334.77,"datetime":"2022-09-19T06:00:00.000+02:00","datetime_utc":"2022-09-19T04:00:00Z","tz_time":"2022-09-19T04:00:00.000Z","geo_id":8745,"geo_name":"Melilla"},{"value":342.06,"datetime":"2022-09-19T07:00:00.000+02:00","datetime_utc":"2022-09-19T05:00:00Z","tz_time":"2022-09-19T05:00:00.000Z","geo_id":8741,"geo_name":"Península"},{"value":342.06,"datetime":"2022-09-19T07:00:00.000+02:00","datetime_utc":"2022-09-19T05:00:00Z","tz_time":"2022-09-19T05:00:00.000Z","geo_id":8742,"geo_name":"Canarias"},{"value":342.06,"datetime":"2022-09-19T07:00:00.000+02:00","datetime_utc":"2022-09-19T05:00:00Z","tz_time":"2022-09-19T05:00:00.000Z","geo_id":8743,"geo_name":"Baleares"},{"value":342.06,"datetime":"2022-09-19T07:00:00.000+02:00","datetime_utc":"2022-09-19T05:00:00Z","tz_time":"2022-09-19T05:00:00.000Z","geo_id":8744,"geo_name":"Ceuta"},{"value":342.06,"datetime":"2022-09-19T07:00:00.000+02:00","datetime_utc":"2022-09-19T05:00:00Z","tz_time":"2022-09-19T05:00:00.000Z","geo_id":8745,"geo_name":"Melilla"},{"value":377.15,"datetime":"2022-09-19T08:00:00.000+02:00","datetime_utc":"2022-09-19T06:00:00Z","tz_time":"2022-09-19T06:00:00.000Z","geo_id":8741,"geo_name":"Península"},{"value":377.15,"datetime":"2022-09-19T08:00:00.000+02:00","datetime_utc":"2022-09-19T06:00:00Z","tz_time":"2022-09-19T06:00:00.000Z","geo_id":8742,"geo_name":"Canarias"},{"value":377.15,"datetime":"2022-09-19T08:00:00.000+02:00","datetime_utc":"2022-09-19T06:00:00Z","tz_time":"2022-09-19T06:00:00.000Z","geo_id":8743,"geo_name":"Baleares"},{"value":377.15,"datetime":"2022-09-19T08:00:00.000+02:00","datetime_utc":"2022-09-19T06:00:00Z","tz_time":"2022-09-19T06:00:00.000Z","geo_id":8744,"geo_name":"Ceuta"},{"value":377.15,"datetime":"2022-09-19T08:00:00.000+02:00","datetime_utc":"2022-09-19T06:00:00Z","tz_time":"2022-09-19T06:00:00.000Z","geo_id":8745,"geo_name":"Melilla"},{"value":354.71,"datetime":"2022-09-19T09:00:00.000+02:00","datetime_utc":"2022-09-19T07:00:00Z","tz_time":"2022-09-19T07:00:00.000Z","geo_id":8741,"geo_name":"Península"},{"value":354.71,"datetime":"2022-09-19T09:00:00.000+02:00","datetime_utc":"2022-09-19T07:00:00Z","tz_time":"2022-09-19T07:00:00.000Z","geo_id":8742,"geo_name":"Canarias"},{"value":354.71,"datetime":"2022-09-19T09:00:00.000+02:00","datetime_utc":"2022-09-19T07:00:00Z","tz_time":"2022-09-19T07:00:00.000Z","geo_id":8743,"geo_name":"Baleares"},{"value":354.71,"datetime":"2022-09-19T09:00:00.000+02:00","datetime_utc":"2022-09-19T07:00:00Z","tz_time":"2022-09-19T07:00:00.000Z","geo_id":8744,"geo_name":"Ceuta"},{"value":354.71,"datetime":"2022-09-19T09:00:00.000+02:00","datetime_utc":"2022-09-19T07:00:00Z","tz_time":"2022-09-19T07:00:00.000Z","geo_id":8745,"geo_name":"Melilla"},{"value":386.96,"datetime":"2022-09-19T10:00:00.000+02:00","datetime_utc":"2022-09-19T08:00:00Z","tz_time":"2022-09-19T08:00:00.000Z","geo_id":8741,"geo_name":"Península"},{"value":386.96,"datetime":"2022-09-19T10:00:00.000+02:00","datetime_utc":"2022-09-19T08:00:00Z","tz_time":"2022-09-19T08:00:00.000Z","geo_id":8742,"geo_name":"Canarias"},{"value":386.96,"datetime":"2022-09-19T10:00:00.000+02:00","datetime_utc":"2022-09-19T08:00:00Z","tz_time":"2022-09-19T08:00:00.000Z","geo_id":8743,"geo_name":"Baleares"},{"value":338.81,"datetime":"2022-09-19T10:00:00.000+02:00","datetime_utc":"2022-09-19T08:00:00Z","tz_time":"2022-09-19T08:00:00.000Z","geo_id":8744,"geo_name":"Ceuta"},{"value":338.81,"datetime":"2022-09-19T10:00:00.000+02:00","datetime_utc":"2022-09-19T08:00:00Z","tz_time":"2022-09-19T08:00:00.000Z","geo_id":8745,"geo_name":"Melilla"},{"value":379.48,"datetime":"2022-09-19T11:00:00.000+02:00","datetime_utc":"2022-09-19T09:00:00Z","tz_time":"2022-09-19T09:00:00.000Z","geo_id":8741,"geo_name":"Península"},{"value":379.48,"datetime":"2022-09-19T11:00:00.000+02:00","datetime_utc":"2022-09-19T09:00:00Z","tz_time":"2022-09-19T09:00:00.000Z","geo_id":8742,"geo_name":"Canarias"},{"value":379.48,"datetime":"2022-09-19T11:00:00.000+02:00","datetime_utc":"2022-09-19T09:00:00Z","tz_time":"2022-09-19T09:00:00.000Z","geo_id":8743,"geo_name":"Baleares"},{"value":379.48,"datetime":"2022-09-19T11:00:00.000+02:00","datetime_utc":"2022-09-19T09:00:00Z","tz_time":"2022-09-19T09:00:00.000Z","geo_id":8744,"geo_name":"Ceuta"},{"value":379.48,"datetime":"2022-09-19T11:00:00.000+02:00","datetime_utc":"2022-09-19T09:00:00Z","tz_time":"2022-09-19T09:00:00.000Z","geo_id":8745,"geo_name":"Melilla"},{"value":377.05,"datetime":"2022-09-19T12:00:00.000+02:00","datetime_utc":"2022-09-19T10:00:00Z","tz_time":"2022-09-19T10:00:00.000Z","geo_id":8741,"geo_name":"Península"},{"value":377.05,"datetime":"2022-09-19T12:00:00.000+02:00","datetime_utc":"2022-09-19T10:00:00Z","tz_time":"2022-09-19T10:00:00.000Z","geo_id":8742,"geo_name":"Canarias"},{"value":377.05,"datetime":"2022-09-19T12:00:00.000+02:00","datetime_utc":"2022-09-19T10:00:00Z","tz_time":"2022-09-19T10:00:00.000Z","geo_id":8743,"geo_name":"Baleares"},{"value":377.05,"datetime":"2022-09-19T12:00:00.000+02:00","datetime_utc":"2022-09-19T10:00:00Z","tz_time":"2022-09-19T10:00:00.000Z","geo_id":8744,"geo_name":"Ceuta"},{"value":377.05,"datetime":"2022-09-19T12:00:00.000+02:00","datetime_utc":"2022-09-19T10:00:00Z","tz_time":"2022-09-19T10:00:00.000Z","geo_id":8745,"geo_name":"Melilla"},{"value":375.38,"datetime":"2022-09-19T13:00:00.000+02:00","datetime_utc":"2022-09-19T11:00:00Z","tz_time":"2022-09-19T11:00:00.000Z","geo_id":8741,"geo_name":"Península"},{"value":375.38,"datetime":"2022-09-19T13:00:00.000+02:00","datetime_utc":"2022-09-19T11:00:00Z","tz_time":"2022-09-19T11:00:00.000Z","geo_id":8742,"geo_name":"Canarias"},{"value":375.38,"datetime":"2022-09-19T13:00:00.000+02:00","datetime_utc":"2022-09-19T11:00:00Z","tz_time":"2022-09-19T11:00:00.000Z","geo_id":8743,"geo_name":"Baleares"},{"value":375.38,"datetime":"2022-09-19T13:00:00.000+02:00","datetime_utc":"2022-09-19T11:00:00Z","tz_time":"2022-09-19T11:00:00.000Z","geo_id":8744,"geo_name":"Ceuta"},{"value":375.38,"datetime":"2022-09-19T13:00:00.000+02:00","datetime_utc":"2022-09-19T11:00:00Z","tz_time":"2022-09-19T11:00:00.000Z","geo_id":8745,"geo_name":"Melilla"},{"value":323.19,"datetime":"2022-09-19T14:00:00.000+02:00","datetime_utc":"2022-09-19T12:00:00Z","tz_time":"2022-09-19T12:00:00.000Z","geo_id":8741,"geo_name":"Península"},{"value":323.19,"datetime":"2022-09-19T14:00:00.000+02:00","datetime_utc":"2022-09-19T12:00:00Z","tz_time":"2022-09-19T12:00:00.000Z","geo_id":8742,"geo_name":"Canarias"},{"value":323.19,"datetime":"2022-09-19T14:00:00.000+02:00","datetime_utc":"2022-09-19T12:00:00Z","tz_time":"2022-09-19T12:00:00.000Z","geo_id":8743,"geo_name":"Baleares"},{"value":371.3,"datetime":"2022-09-19T14:00:00.000+02:00","datetime_utc":"2022-09-19T12:00:00Z","tz_time":"2022-09-19T12:00:00.000Z","geo_id":8744,"geo_name":"Ceuta"},{"value":371.3,"datetime":"2022-09-19T14:00:00.000+02:00","datetime_utc":"2022-09-19T12:00:00Z","tz_time":"2022-09-19T12:00:00.000Z","geo_id":8745,"geo_name":"Melilla"},{"value":320.78,"datetime":"2022-09-19T15:00:00.000+02:00","datetime_utc":"2022-09-19T13:00:00Z","tz_time":"2022-09-19T13:00:00.000Z","geo_id":8741,"geo_name":"Península"},{"value":320.78,"datetime":"2022-09-19T15:00:00.000+02:00","datetime_utc":"2022-09-19T13:00:00Z","tz_time":"2022-09-19T13:00:00.000Z","geo_id":8742,"geo_name":"Canarias"},{"value":320.78,"datetime":"2022-09-19T15:00:00.000+02:00","datetime_utc":"2022-09-19T13:00:00Z","tz_time":"2022-09-19T13:00:00.000Z","geo_id":8743,"geo_name":"Baleares"},{"value":320.78,"datetime":"2022-09-19T15:00:00.000+02:00","datetime_utc":"2022-09-19T13:00:00Z","tz_time":"2022-09-19T13:00:00.000Z","geo_id":8744,"geo_name":"Ceuta"},{"value":320.78,"datetime":"2022-09-19T15:00:00.000+02:00","datetime_utc":"2022-09-19T13:00:00Z","tz_time":"2022-09-19T13:00:00.000Z","geo_id":8745,"geo_name":"Melilla"},{"value":327.82,"datetime":"2022-09-19T16:00:00.000+02:00","datetime_utc":"2022-09-19T14:00:00Z","tz_time":"2022-09-19T14:00:00.000Z","geo_id":8741,"geo_name":"Península"},{"value":327.82,"datetime":"2022-09-19T16:00:00.000+02:00","datetime_utc":"2022-09-19T14:00:00Z","tz_time":"2022-09-19T14:00:00.000Z","geo_id":8742,"geo_name":"Canarias"},{"value":327.82,"datetime":"2022-09-19T16:00:00.000+02:00","datetime_utc":"2022-09-19T14:00:00Z","tz_time":"2022-09-19T14:00:00.000Z","geo_id":8743,"geo_name":"Baleares"},{"value":327.82,"datetime":"2022-09-19T16:00:00.000+02:00","datetime_utc":"2022-09-19T14:00:00Z","tz_time":"2022-09-19T14:00:00.000Z","geo_id":8744,"geo_name":"Ceuta"},{"value":327.82,"datetime":"2022-09-19T16:00:00.000+02:00","datetime_utc":"2022-09-19T14:00:00Z","tz_time":"2022-09-19T14:00:00.000Z","geo_id":8745,"geo_name":"Melilla"},{"value":327.85,"datetime":"2022-09-19T17:00:00.000+02:00","datetime_utc":"2022-09-19T15:00:00Z","tz_time":"2022-09-19T15:00:00.000Z","geo_id":8741,"geo_name":"Península"},{"value":327.85,"datetime":"2022-09-19T17:00:00.000+02:00","datetime_utc":"2022-09-19T15:00:00Z","tz_time":"2022-09-19T15:00:00.000Z","geo_id":8742,"geo_name":"Canarias"},{"value":327.85,"datetime":"2022-09-19T17:00:00.000+02:00","datetime_utc":"2022-09-19T15:00:00Z","tz_time":"2022-09-19T15:00:00.000Z","geo_id":8743,"geo_name":"Baleares"},{"value":327.85,"datetime":"2022-09-19T17:00:00.000+02:00","datetime_utc":"2022-09-19T15:00:00Z","tz_time":"2022-09-19T15:00:00.000Z","geo_id":8744,"geo_name":"Ceuta"},{"value":327.85,"datetime":"2022-09-19T17:00:00.000+02:00","datetime_utc":"2022-09-19T15:00:00Z","tz_time":"2022-09-19T15:00:00.000Z","geo_id":8745,"geo_name":"Melilla"},{"value":393.08,"datetime":"2022-09-19T18:00:00.000+02:00","datetime_utc":"2022-09-19T16:00:00Z","tz_time":"2022-09-19T16:00:00.000Z","geo_id":8741,"geo_name":"Península"},{"value":393.08,"datetime":"2022-09-19T18:00:00.000+02:00","datetime_utc":"2022-09-19T16:00:00Z","tz_time":"2022-09-19T16:00:00.000Z","geo_id":8742,"geo_name":"Canarias"},{"value":393.08,"datetime":"2022-09-19T18:00:00.000+02:00","datetime_utc":"2022-09-19T16:00:00Z","tz_time":"2022-09-19T16:00:00.000Z","geo_id":8743,"geo_name":"Baleares"},{"value":344.91,"datetime":"2022-09-19T18:00:00.000+02:00","datetime_utc":"2022-09-19T16:00:00Z","tz_time":"2022-09-19T16:00:00.000Z","geo_id":8744,"geo_name":"Ceuta"},{"value":344.91,"datetime":"2022-09-19T18:00:00.000+02:00","datetime_utc":"2022-09-19T16:00:00Z","tz_time":"2022-09-19T16:00:00.000Z","geo_id":8745,"geo_name":"Melilla"},{"value":404.7,"datetime":"2022-09-19T19:00:00.000+02:00","datetime_utc":"2022-09-19T17:00:00Z","tz_time":"2022-09-19T17:00:00.000Z","geo_id":8741,"geo_name":"Península"},{"value":404.7,"datetime":"2022-09-19T19:00:00.000+02:00","datetime_utc":"2022-09-19T17:00:00Z","tz_time":"2022-09-19T17:00:00.000Z","geo_id":8742,"geo_name":"Canarias"},{"value":404.7,"datetime":"2022-09-19T19:00:00.000+02:00","datetime_utc":"2022-09-19T17:00:00Z","tz_time":"2022-09-19T17:00:00.000Z","geo_id":8743,"geo_name":"Baleares"},{"value":404.7,"datetime":"2022-09-19T19:00:00.000+02:00","datetime_utc":"2022-09-19T17:00:00Z","tz_time":"2022-09-19T17:00:00.000Z","geo_id":8744,"geo_name":"Ceuta"},{"value":404.7,"datetime":"2022-09-19T19:00:00.000+02:00","datetime_utc":"2022-09-19T17:00:00Z","tz_time":"2022-09-19T17:00:00.000Z","geo_id":8745,"geo_name":"Melilla"},{"value":453.97,"datetime":"2022-09-19T20:00:00.000+02:00","datetime_utc":"2022-09-19T18:00:00Z","tz_time":"2022-09-19T18:00:00.000Z","geo_id":8741,"geo_name":"Península"},{"value":453.97,"datetime":"2022-09-19T20:00:00.000+02:00","datetime_utc":"2022-09-19T18:00:00Z","tz_time":"2022-09-19T18:00:00.000Z","geo_id":8742,"geo_name":"Canarias"},{"value":453.97,"datetime":"2022-09-19T20:00:00.000+02:00","datetime_utc":"2022-09-19T18:00:00Z","tz_time":"2022-09-19T18:00:00.000Z","geo_id":8743,"geo_name":"Baleares"},{"value":453.97,"datetime":"2022-09-19T20:00:00.000+02:00","datetime_utc":"2022-09-19T18:00:00Z","tz_time":"2022-09-19T18:00:00.000Z","geo_id":8744,"geo_name":"Ceuta"},{"value":453.97,"datetime":"2022-09-19T20:00:00.000+02:00","datetime_utc":"2022-09-19T18:00:00Z","tz_time":"2022-09-19T18:00:00.000Z","geo_id":8745,"geo_name":"Melilla"},{"value":435.44,"datetime":"2022-09-19T21:00:00.000+02:00","datetime_utc":"2022-09-19T19:00:00Z","tz_time":"2022-09-19T19:00:00.000Z","geo_id":8741,"geo_name":"Península"},{"value":435.44,"datetime":"2022-09-19T21:00:00.000+02:00","datetime_utc":"2022-09-19T19:00:00Z","tz_time":"2022-09-19T19:00:00.000Z","geo_id":8742,"geo_name":"Canarias"},{"value":435.44,"datetime":"2022-09-19T21:00:00.000+02:00","datetime_utc":"2022-09-19T19:00:00Z","tz_time":"2022-09-19T19:00:00.000Z","geo_id":8743,"geo_name":"Baleares"},{"value":435.44,"datetime":"2022-09-19T21:00:00.000+02:00","datetime_utc":"2022-09-19T19:00:00Z","tz_time":"2022-09-19T19:00:00.000Z","geo_id":8744,"geo_name":"Ceuta"},{"value":435.44,"datetime":"2022-09-19T21:00:00.000+02:00","datetime_utc":"2022-09-19T19:00:00Z","tz_time":"2022-09-19T19:00:00.000Z","geo_id":8745,"geo_name":"Melilla"},{"value":358.71,"datetime":"2022-09-19T22:00:00.000+02:00","datetime_utc":"2022-09-19T20:00:00Z","tz_time":"2022-09-19T20:00:00.000Z","geo_id":8741,"geo_name":"Península"},{"value":358.71,"datetime":"2022-09-19T22:00:00.000+02:00","datetime_utc":"2022-09-19T20:00:00Z","tz_time":"2022-09-19T20:00:00.000Z","geo_id":8742,"geo_name":"Canarias"},{"value":358.71,"datetime":"2022-09-19T22:00:00.000+02:00","datetime_utc":"2022-09-19T20:00:00Z","tz_time":"2022-09-19T20:00:00.000Z","geo_id":8743,"geo_name":"Baleares"},{"value":406.92,"datetime":"2022-09-19T22:00:00.000+02:00","datetime_utc":"2022-09-19T20:00:00Z","tz_time":"2022-09-19T20:00:00.000Z","geo_id":8744,"geo_name":"Ceuta"},{"value":406.92,"datetime":"2022-09-19T22:00:00.000+02:00","datetime_utc":"2022-09-19T20:00:00Z","tz_time":"2022-09-19T20:00:00.000Z","geo_id":8745,"geo_name":"Melilla"},{"value":343.15,"datetime":"2022-09-19T23:00:00.000+02:00","datetime_utc":"2022-09-19T21:00:00Z","tz_time":"2022-09-19T21:00:00.000Z","geo_id":8741,"geo_name":"Península"},{"value":343.15,"datetime":"2022-09-19T23:00:00.000+02:00","datetime_utc":"2022-09-19T21:00:00Z","tz_time":"2022-09-19T21:00:00.000Z","geo_id":8742,"geo_name":"Canarias"},{"value":343.15,"datetime":"2022-09-19T23:00:00.000+02:00","datetime_utc":"2022-09-19T21:00:00Z","tz_time":"2022-09-19T21:00:00.000Z","geo_id":8743,"geo_name":"Baleares"},{"value":343.15,"datetime":"2022-09-19T23:00:00.000+02:00","datetime_utc":"2022-09-19T21:00:00Z","tz_time":"2022-09-19T21:00:00.000Z","geo_id":8744,"geo_name":"Ceuta"},{"value":343.15,"datetime":"2022-09-19T23:00:00.000+02:00","datetime_utc":"2022-09-19T21:00:00Z","tz_time":"2022-09-19T21:00:00.000Z","geo_id":8745,"geo_name":"Melilla"}]}}