{"indicator":{"name":"Termino de facturacion de energia activa del PVPC 2.0TD","short_name":"PVPC T. 2.0TD","id":1001,"composited":false,"step_type":"linear","disaggregated":true,"magnitud":[{"name":"Precio","id":23}],"tiempo":[{"name":"Hora","id":4}],"geos":[{"geo_id":8741,"geo_name":"Peninsula"},{"geo_id":8742,"geo_name":"Canarias"},{"geo_id":8743,"geo_name":"Baleares"},{"geo_id":8744,"geo_name":"Ceuta"},{"geo_id":8745,"geo_name":"Melilla"}],"values_updated_at":"2022-04-25T20:17:05.000+02:00","values":[{"value":292.98,"datetime":"2022-04-26T00:00:00.000+02:00","datetime_utc":"2022-04-25T22:00:00Z","tz_time":"2022-04-25T22:00:00.000Z","geo_id":8741,"geo_name":"Peninsula"},{"value":292.98,"datetime":"2022-04-26T00:00:00.000+02:00","datetime_utc":"2022-04-25T22:00:00Z","tz_time":"2022-04-25T22:00:00.000Z","geo_id":8742,"geo_name":"Canarias"},{"value":292.98,"datetime":"2022-04-26T00:00:00.000+02:00","datetime_utc":"2022-04-25T22:00:00Z","tz_time":"2022-04-25T22:00:00.000Z","geo_id":8743,"geo_name":"Baleares"},{"value":292.98,"datetime":"2022-04-26T00:00:00.000+02:00","datetime_utc":"2022-04-25T22:00:00Z","tz_time":"2022-04-25T22:00:00.000Z","geo_id":8744,"geo_name":"Ceuta"},{"value":292.98,"datetime":"2022-04-26T00:00:00.000+02:00","datetime_utc":"2022-04-25T22:00:00Z","tz_time":"2022-04-25T22:00:00.000Z","geo_id":8745,"geo_name":"Melilla"},{"value":290.77,"datetime":"2022-04-26T01:00:00.000+02:00","datetime_utc":"2022-04-25T23:00:00Z","tz_time":"2022-04-25T23:00:00.000Z","geo_id":8741,"geo_name":"Peninsula"},{"value":290.77,"datetime":"2022-04-26T01:00:00.000+02:00","datetime_utc":"2022-04-25T23:00:00Z","tz_time":"2022-04-25T23:00:00.000Z","geo_id":8742,"geo_name":"Canarias"},{"value":290.77,"datetime":"2022-04-26T01:00:00.000+02:00","datetime_utc":"2022-04-25T23:00:00Z","tz_time":"2022-04-25T23:00:00.000Z","geo_id":8743,"geo_name":"Baleares"},{"value":290.77,"datetime":"2022-04-26T01:00:00.000+02:00","datetime_utc":"2022-04-25T23:00:00Z","tz_time":"2022-04-25T23:00:00.000Z","geo_id":8744,"geo_name":"Ceuta"},{"value":290.77,"datetime":"2022-04-26T01:00:00.000+02:00","datetime_utc":"2022-04-25T23:00:00Z","tz_time":"2022-04-25T23:00:00.000Z","geo_id":8745,"geo_name":"Melilla"},{"value":281.44,"datetime":"2022-04-26T02:00:00.000+02:00","datetime_utc":"2022-04-26T00:00:00Z","tz_time":"2022-04-26T00:00:00.000Z","geo_id":8741,"geo_name":"Peninsula"},{"value":281.44,"datetime":"2022-04-26T02:00:00.000+02:00","datetime_utc":"2022-04-26T00:00:00Z","tz_time":"2022-04-26T00:00:00.000Z","geo_id":8742,"geo_name":"Canarias"},{"value":281.44,"datetime":"2022-04-26T02:00:00.000+02:00","datetime_utc":"2022-04-26T00:00:00Z","tz_time":"2022-04-26T00:00:00.000Z","geo_id":8743,"geo_name":"Baleares"},{"value":281.44,"datetime":"2022-04-26T02:00:00.000+02:00","datetime_utc":"2022-04-26T00:00:00Z","tz_time":"2022-04-26T00:00:00.000Z","geo_id":8744,"geo_name":"Ceuta"},{"value":281.44,"datetime":"2022-04-26T02:00:00.000+02:00","datetime_utc":"2022-04-26T00:00:00Z","tz_time":"2022-04-26T00:00:00.000Z","geo_id":8745,"geo_name":"Melilla"},{"value":269.81,"datetime":"2022-04-26T03:00:00.000+02:00","datetime_utc":"2022-04-26T01:00:00Z","tz_time":"2022-04-26T01:00:00.000Z","geo_id":8741,"geo_name":"Peninsula"},{"value":269.81,"datetime":"2022-04-26T03:00:00.000+02:00","datetime_utc":"2022-04-26T01:00:00Z","tz_time":"2022-04-26T01:00:00.000Z","geo_id":8742,"geo_name":"Canarias"},{"value":269.81,"datetime":"2022-04-26T03:00:00.000+02:00","datetime_utc":"2022-04-26T01:00:00Z","tz_time":"2022-04-26T01:00:00.000Z","geo_id":8743,"geo_name":"Baleares"},{"value":269.81,"datetime":"2022-04-26T03:00:00.000+02:00","datetime_utc":"2022-04-26T01:00:00Z","tz_time":"2022-04-26T01:00:00.000Z","geo_id":8744,"geo_name":"Ceuta"},{"value":269.81,"datetime":"2022-04-26T03:00:00.000+02:00","datetime_utc":"2022-04-26T01:00:00Z","tz_time":"2022-04-26T01:00:00.000Z","geo_id":8745,"geo_name":"Melilla"},{"value":273.73,"datetime":"2022-04-26T04:00:00.000+02:00","datetime_utc":"2022-04-26T02:00:00Z","tz_time":"2022-04-26T02:00:00.000Z","geo_id":8741,"geo_name":"Peninsula"},{"value":273.73,"datetime":"2022-04-26T04:00:00.000+02:00","datetime_utc":"2022-04-26T02:00:00Z","tz_time":"2022-04-26T02:00:00.000Z","geo_id":8742,"geo_name":"Canarias"},{"value":273.73,"datetime":"2022-04-26T04:00:00.000+02:00","datetime_utc":"2022-04-26T02:00:00Z","tz_time":"2022-04-26T02:00:00.000Z","geo_id":8743,"geo_name":"Baleares"},{"value":273.73,"datetime":"2022-04-26T04:00:00.000+02:00","datetime_utc":"2022-04-26T02:00:00Z","tz_time":"2022-04-26T02:00:00.000Z","geo_id":8744,"geo_name":"Ceuta"},{"value":273.73,"datetime":"2022-04-26T04:00:00.000+02:00","datetime_utc":"2022-04-26T02:00:00Z","tz_time":"2022-04-26T02:00:00.000Z","geo_id":8745,"geo_name":"Melilla"},{"value":294.32,"datetime":"2022-04-26T05:00:00.000+02:00","datetime_utc":"2022-04-26T03:00:00Z","tz_time":"2022-04-26T03:00:00.000Z","geo_id":8741,"geo_name":"Peninsula"},{"value":294.32,"datetime":"2022-04-26T05:00:00.000+02:00","datetime_utc":"2022-04-26T03:00:00Z","tz_time":"2022-04-26T03:00:00.000Z","geo_id":8742,"geo_name":"Canarias"},{"value":294.32,"datetime":"2022-04-26T05:00:00.000+02:00","datetime_utc":"2022-04-26T03:00:00Z","tz_time":"2022-04-26T03:00:00.000Z","geo_id":8743,"geo_name":"Baleares"},{"value":294.32,"datetime":"2022-04-26T05:00:00.000+02:00","datetime_utc":"2022-04-26T03:00:00Z","tz_time":"2022-04-26T03:00:00.000Z","geo_id":8744,"geo_name":"Ceuta"},{"value":294.32,"datetime":"2022-04-26T05:00:00.000+02:00","datetime_utc":"2022-04-26T03:00:00Z","tz_time":"2022-04-26T03:00:00.000Z","geo_id":8745,"geo_name":"Melilla"},{"value":313.2,"datetime":"2022-04-26T06:00:00.000+02:00","datetime_utc":"2022-04-26T04:00:00Z","tz_time":"2022-04-26T04:00:00.000Z","geo_id":8741,"geo_name":"Peninsula"},{"value":313.2,"datetime":"2022-04-26T06:00:00.000+02:00","datetime_utc":"2022-04-26T04:00:00Z","tz_time":"2022-04-26T04:00:00.000Z","geo_id":8742,"geo_name":"Canarias"},{"value":313.2,"datetime":"2022-04-26T06:00:00.000+02:00","datetime_utc":"2022-04-26T04:00:00Z","tz_time":"2022-04-26T04:00:00.000Z","geo_id":8743,"geo_name":"Baleares"},{"value":313.2,"datetime":"2022-04-26T06:00:00.000+02:00","datetime_utc":"2022-04-26T04:00:00Z","tz_time":"2022-04-26T04:00:00.000Z","geo_id":8744,"geo_name":"Ceuta"},{"value":313.2,"datetime":"2022-04-26T06:00:00.000+02:00","datetime_utc":"2022-04-26T04:00:00Z","tz_time":"2022-04-26T04:00:00.000Z","geo_id":8745,"geo_name":"Melilla"},{"value":314.92,"datetime":"2022-04-26T07:00:00.000+02:00","datetime_utc":"2022-04-26T05:00:00Z","tz_time":"2022-04-26T05:00:00.000Z","geo_id":8741,"geo_name":"Peninsula"},{"value":314.92,"datetime":"2022-04-26T07:00:00.000+02:00","datetime_utc":"2022-04-26T05:00:00Z","tz_time":"2022-04-26T05:00:00.000Z","geo_id":8742,"geo_name":"Canarias"},{"value":314.92,"datetime":"2022-04-26T07:00:00.000+02:00","datetime_utc":"2022-04-26T05:00:00Z","tz_time":"2022-04-26T05:00:00.000Z","geo_id":8743,"geo_name":"Baleares"},{"value":314.92,"datetime":"2022-04-26T07:00:00.000+02:00","datetime_utc":"2022-04-26T05:00:00Z","tz_time":"2022-04-26T05:00:00.000Z","geo_id":8744,"geo_name":"Ceuta"},{"value":314.92,"datetime":"2022-04-26T07:00:00.000+02:00","datetime_utc":"2022-04-26T05:00:00Z","tz_time":"2022-04-26T05:00:00.000Z","geo_id":8745,"geo_name":"Melilla"},{"value":347.84,"datetime":"2022-04-26T08:00:00.000+02:00","datetime_utc":"2022-04-26T06:00:00Z","tz_time":"2022-04-26T06:00:00.000Z","geo_id":8741,"geo_name":"Peninsula"},{"value":347.84,"datetime":"2022-04-26T08:00:00.000+02:00","datetime_utc":"2022-04-26T06:00:00Z","tz_time":"2022-04-26T06:00:00.000Z","geo_id":8742,"geo_name":"Canarias"},{"value":347.84,"datetime":"2022-04-26T08:00:00.000+02:00","datetime_utc":"2022-04-26T06:00:00Z","tz_time":"2022-04-26T06:00:00.000Z","geo_id":8743,"geo_name":"Baleares"},{"value":347.84,"datetime":"2022-04-26T08:00:00.000+02:00","datetime_utc":"2022-04-26T06:00:00Z","tz_time":"2022-04-26T06:00:00.000Z","geo_id":8744,"geo_name":"Ceuta"},{"value":347.84,"datetime":"2022-04-26T08:00:00.000+02:00","datetime_utc":"2022-04-26T06:00:00Z","tz_time":"2022-04-26T06:00:00.000Z","geo_id":8745,"geo_name":"Melilla"},{"value":326.2,"datetime":"2022-04-26T09:00:00.000+02:00","datetime_utc":"2022-04-26T07:00:00Z","tz_time":"2022-04-26T07:00:00.000Z","geo_id":8741,"geo_name":"Peninsula"},{"value":326.2,"datetime":"2022-04-26T09:00:00.000+02:00","datetime_utc":"2022-04-26T07:00:00Z","tz_time":"2022-04-26T07:00:00.000Z","geo_id":8742,"geo_name":"Canarias"},{"value":326.2,"datetime":"2022-04-26T09:00:00.000+02:00","datetime_utc":"2022-04-26T07:00:00Z","tz_time":"2022-04-26T07:00:00.000Z","geo_id":8743,"geo_name":"Baleares"},{"value":326.2,"datetime":"2022-04-26T09:00:00.000+02:00","datetime_utc":"2022-04-26T07:00:00Z","tz_time":"2022-04-26T07:00:00.000Z","geo_id":8744,"geo_name":"Ceuta"},{"value":326.2,"datetime":"2022-04-26T09:00:00.000+02:00","datetime_utc":"2022-04-26T07:00:00Z","tz_time":"2022-04-26T07:00:00.000Z","geo_id":8745,"geo_name":"Melilla"},{"value":362.81,"datetime":"2022-04-26T10:00:00.000+02:00","datetime_utc":"2022-04-26T08:00:00Z","tz_time":"2022-04-26T08:00:00.000Z","geo_id":8741,"geo_name":"Peninsula"},{"value":362.81,"datetime":"2022-04-26T10:00:00.000+02:00","datetime_utc":"2022-04-26T08:00:00Z","tz_time":"2022-04-26T08:00:00.000Z","geo_id":8742,"geo_name":"Canarias"},{"value":362.81,"datetime":"2022-04-26T10:00:00.000+02:00","datetime_utc":"2022-04-26T08:00:00Z","tz_time":"2022-04-26T08:00:00.000Z","geo_id":8743,"geo_name":"Baleares"},{"value":314.45,"datetime":"2022-04-26T10:00:00.000+02:00","datetime_utc":"2022-04-26T08:00:00Z","tz_time":"2022-04-26T08:00:00.000Z","geo_id":8744,"geo_name":"Ceuta"},{"value":314.45,"datetime":"2022-04-26T10:00:00.000+02:00","datetime_utc":"2022-04-26T08:00:00Z","tz_time":"2022-04-26T08:00:00.000Z","geo_id":8745,"geo_name":"Melilla"},{"value":349.8,"datetime":"2022-04-26T11:00:00.000+02:00","datetime_utc":"2022-04-26T09:00:00Z","tz_time":"2022-04-26T09:00:00.000Z","geo_id":8741,"geo_name":"Peninsula"},{"value":349.8,"datetime":"2022-04-26T11:00:00.000+02:00","datetime_utc":"2022-04-26T09:00:00Z","tz_time":"2022-04-26T09:00:00.000Z","geo_id":8742,"geo_name":"Canarias"},{"value":349.8,"datetime":"2022-04-26T11:00:00.000+02:00","datetime_utc":"2022-04-26T09:00:00Z","tz_time":"2022-04-26T09:00:00.000Z","geo_id":8743,"geo_name":"Baleares"},{"value":349.8,"datetime":"2022-04-26T11:00:00.000+02:00","datetime_utc":"2022-04-26T09:00:00Z","tz_time":"2022-04-26T09:00:00.000Z","geo_id":8744,"geo_name":"Ceuta"},{"value":349.8,"datetime":"2022-04-26T11:00:00.000+02:00","datetime_utc":"2022-04-26T09:00:00Z","tz_time":"2022-04-26T09:00:00.000Z","geo_id":8745,"geo_name":"Melilla"},{"value":342.18,"datetime":"2022-04-26T12:00:00.000+02:00","datetime_utc":"2022-04-26T10:00:00Z","tz_time":"2022-04-26T10:00:00.000Z","geo_id":8741,"geo_name":"Peninsula"},{"value":342.18,"datetime":"2022-04-26T12:00:00.000+02:00","datetime_utc":"2022-04-26T10:00:00Z","tz_time":"2022-04-26T10:00:00.000Z","geo_id":8742,"geo_name":"Canarias"},{"value":342.18,"datetime":"2022-04-26T12:00:00.000+02:00","datetime_utc":"2022-04-26T10:00:00Z","tz_time":"2022-04-26T10:00:00.000Z","geo_id":8743,"geo_name":"Baleares"},{"value":342.18,"datetime":"2022-04-26T12:00:00.000+02:00","datetime_utc":"2022-04-26T10:00:00Z","tz_time":"2022-04-26T10:00:00.000Z","geo_id":8744,"geo_name":"Ceuta"},{"value":342.18,"datetime":"2022-04-26T12:00:00.000+02:00","datetime_utc":"2022-04-26T10:00:00Z","tz_time":"2022-04-26T10:00:00.000Z","geo_id":8745,"geo_name":"Melilla"},{"value":331.29,"datetime":"2022-04-26T13:00:00.000+02:00","datetime_utc":"2022-04-26T11:00:00Z","tz_time":"2022-04-26T11:00:00.000Z","geo_id":8741,"geo_name":"Peninsula"},{"value":331.29,"datetime":"2022-04-26T13:00:00.000+02:00","datetime_utc":"2022-04-26T11:00:00Z","tz_time":"2022-04-26T11:00:00.000Z","geo_id":8742,"geo_name":"Canarias"},{"value":331.29,"datetime":"2022-04-26T13:00:00.000+02:00","datetime_utc":"2022-04-26T11:00:00Z","tz_time":"2022-04-26T11:00:00.000Z","geo_id":8743,"geo_name":"Baleares"},{"value":331.29,"datetime":"2022-04-26T13:00:00.000+02:00","datetime_utc":"2022-04-26T11:00:00Z","tz_time":"2022-04-26T11:00:00.000Z","geo_id":8744,"geo_name":"Ceuta"},{"value":331.29,"datetime":"2022-04-26T13:00:00.000+02:00","datetime_utc":"2022-04-26T11:00:00Z","tz_time":"2022-04-26T11:00:00.000Z","geo_id":8745,"geo_name":"Melilla"},{"value":275.56,"datetime":"2022-04-26T14:00:00.000+02:00","datetime_utc":"2022-04-26T12:00:00Z","tz_time":"2022-04-26T12:00:00.000Z","geo_id":8741,"geo_name":"Peninsula"},{"value":275.56,"datetime":"2022-04-26T14:00:00.000+02:00","datetime_utc":"2022-04-26T12:00:00Z","tz_time":"2022-04-26T12:00:00.000Z","geo_id":8742,"geo_name":"Canarias"},{"value":275.56,"datetime":"2022-04-26T14:00:00.000+02:00","datetime_utc":"2022-04-26T12:00:00Z","tz_time":"2022-04-26T12:00:00.000Z","geo_id":8743,"geo_name":"Baleares"},{"value":323.78,"datetime":"2022-04-26T14:00:00.000+02:00","datetime_utc":"2022-04-26T12:00:00Z","tz_time":"2022-04-26T12:00:00.000Z","geo_id":8744,"geo_name":"Ceuta"},{"value":323.78,"datetime":"2022-04-26T14:00:00.000+02:00","datetime_utc":"2022-04-26T12:00:00Z","tz_time":"2022-04-26T12:00:00.000Z","geo_id":8745,"geo_name":"Melilla"},{"value":278.96,"datetime":"2022-04-26T15:00:00.000+02:00","datetime_utc":"2022-04-26T13:00:00Z","tz_time":"2022-04-26T13:00:00.000Z","geo_id":8741,"geo_name":"Peninsula"},{"value":278.96,"datetime":"2022-04-26T15:00:00.000+02:00","datetime_utc":"2022-04-26T13:00:00Z","tz_time":"2022-04-26T13:00:00.000Z","geo_id":8742,"geo_name":"Canarias"},{"value":278.96,"datetime":"2022-04-26T15:00:00.000+02:00","datetime_utc":"2022-04-26T13:00:00Z","tz_time":"2022-04-26T13:00:00.000Z","geo_id":8743,"geo_name":"Baleares"},{"value":278.96,"datetime":"2022-04-26T15:00:00.000+02:00","datetime_utc":"2022-04-26T13:00:00Z","tz_time":"2022-04-26T13:00:00.000Z","geo_id":8744,"geo_name":"Ceuta"},{"value":278.96,"datetime":"2022-04-26T15:00:00.000+02:00","datetime_utc":"2022-04-26T13:00:00Z","tz_time":"2022-04-26T13:00:00.000Z","geo_id":8745,"geo_name":"Melilla"},{"value":283.17,"datetime":"2022-04-26T16:00:00.000+02:00","datetime_utc":"2022-04-26T14:00:00Z","tz_time":"2022-04-26T14:00:00.000Z","geo_id":8741,"geo_name":"Peninsula"},{"value":283.17,"datetime":"2022-04-26T16:00:00.000+02:00","datetime_utc":"2022-04-26T14:00:00Z","tz_time":"2022-04-26T14:00:00.000Z","geo_id":8742,"geo_name":"Canarias"},{"value":283.17,"datetime":"2022-04-26T16:00:00.000+02:00","datetime_utc":"2022-04-26T14:00:00Z","tz_time":"2022-04-26T14:00:00.000Z","geo_id":8743,"geo_name":"Baleares"},{"value":283.17,"datetime":"2022-04-26T16:00:00.000+02:00","datetime_utc":"2022-04-26T14:00:00Z","tz_time":"2022-04-26T14:00:00.000Z","geo_id":8744,"geo_name":"Ceuta"},{"value":283.17,"datetime":"2022-04-26T16:00:00.000+02:00","datetime_utc":"2022-04-26T14:00:00Z","tz_time":"2022-04-26T14:00:00.000Z","geo_id":8745,"geo_name":"Melilla"},{"value":303.4,"datetime":"2022-04-26T17:00:00.000+02:00","datetime_utc":"2022-04-26T15:00:00Z","tz_time":"2022-04-26T15:00:00.000Z","geo_id":8741,"geo_name":"Peninsula"},{"value":303.4,"datetime":"2022-04-26T17:00:00.000+02:00","datetime_utc":"2022-04-26T15:00:00Z","tz_time":"2022-04-26T15:00:00.000Z","geo_id":8742,"geo_name":"Canarias"},{"value":303.4,"datetime":"2022-04-26T17:00:00.000+02:00","datetime_utc":"2022-04-26T15:00:00Z","tz_time":"2022-04-26T15:00:00.000Z","geo_id":8743,"geo_name":"Baleares"},{"value":303.4,"datetime":"2022-04-26T17:00:00.000+02:00","datetime_utc":"2022-04-26T15:00:00Z","tz_time":"2022-04-26T15:00:00.000Z","geo_id":8744,"geo_name":"Ceuta"},{"value":303.4,"datetime":"2022-04-26T17:00:00.000+02:00","datetime_utc":"2022-04-26T15:00:00Z","tz_time":"2022-04-26T15:00:00.000Z","geo_id":8745,"geo_name":"Melilla"},{"value":355.22,"datetime":"2022-04-26T18:00:00.000+02:00","datetime_utc":"2022-04-26T16:00:00Z","tz_time":"2022-04-26T16:00:00.000Z","geo_id":8741,"geo_name":"Peninsula"},{"value":355.22,"datetime":"2022-04-26T18:00:00.000+02:00","datetime_utc":"2022-04-26T16:00:00Z","tz_time":"2022-04-26T16:00:00.000Z","geo_id":8742,"geo_name":"Canarias"},{"value":355.22,"datetime":"2022-04-26T18:00:00.000+02:00","datetime_utc":"2022-04-26T16:00:00Z","tz_time":"2022-04-26T16:00:00.000Z","geo_id":8743,"geo_name":"Baleares"},{"value":306.89,"datetime":"2022-04-26T18:00:00.000+02:00","datetime_utc":"2022-04-26T16:00:00Z","tz_time":"2022-04-26T16:00:00.000Z","geo_id":8744,"geo_name":"Ceuta"},{"value":306.89,"datetime":"2022-04-26T18:00:00.000+02:00","datetime_utc":"2022-04-26T16:00:00Z","tz_time":"2022-04-26T16:00:00.000Z","geo_id":8745,"geo_name":"Melilla"},{"value":371.82,"datetime":"2022-04-26T19:00:00.000+02:00","datetime_utc":"2022-04-26T17:00:00Z","tz_time":"2022-04-26T17:00:00.000Z","geo_id":8741,"geo_name":"Peninsula"},{"value":371.82,"datetime":"2022-04-26T19:00:00.000+02:00","datetime_utc":"2022-04-26T17:00:00Z","tz_time":"2022-04-26T17:00:00.000Z","geo_id":8742,"geo_name":"Canarias"},{"value":371.82,"datetime":"2022-04-26T19:00:00.000+02:00","datetime_utc":"2022-04-26T17:00:00Z","tz_time":"2022-04-26T17:00:00.000Z","geo_id":8743,"geo_name":"Baleares"},{"value":371.82,"datetime":"2022-04-26T19:00:00.000+02:00","datetime_utc":"2022-04-26T17:00:00Z","tz_time":"2022-04-26T17:00:00.000Z","geo_id":8744,"geo_name":"Ceuta"},{"value":371.82,"datetime":"2022-04-26T19:00:00.000+02:00","datetime_utc":"2022-04-26T17:00:00Z","tz_time":"2022-04-26T17:00:00.000Z","geo_id":8745,"geo_name":"Melilla"},{"value":397.56,"datetime":"2022-04-26T20:00:00.000+02:00","datetime_utc":"2022-04-26T18:00:00Z","tz_time":"2022-04-26T18:00:00.000Z","geo_id":8741,"geo_name":"Peninsula"},{"value":397.56,"datetime":"2022-04-26T20:00:00.000+02:00","datetime_utc":"2022-04-26T18:00:00Z","tz_time":"2022-04-26T18:00:00.000Z","geo_id":8742,"geo_name":"Canarias"},{"value":397.56,"datetime":"2022-04-26T20:00:00.000+02:00","datetime_utc":"2022-04-26T18:00:00Z","tz_time":"2022-04-26T18:00:00.000Z","geo_id":8743,"geo_name":"Baleares"},{"value":397.56,"datetime":"2022-04-26T20:00:00.000+02:00","datetime_utc":"2022-04-26T18:00:00Z","tz_time":"2022-04-26T18:00:00.000Z","geo_id":8744,"geo_name":"Ceuta"},{"value":397.56,"datetime":"2022-04-26T20:00:00.000+02:00","datetime_utc":"2022-04-26T18:00:00Z","tz_time":"2022-04-26T18:00:00.000Z","geo_id":8745,"geo_name":"Melilla"},{"value":397.34,"datetime":"2022-04-26T21:00:00.000+02:00","datetime_utc":"2022-04-26T19:00:00Z","tz_time":"2022-04-26T19:00:00.000Z","geo_id":8741,"geo_name":"Peninsula"},{"value":397.34,"datetime":"2022-04-26T21:00:00.000+02:00","datetime_utc":"2022-04-26T19:00:00Z","tz_time":"2022-04-26T19:00:00.000Z","geo_id":8742,"geo_name":"Canarias"},{"value":397.34,"datetime":"2022-04-26T21:00:00.000+02:00","datetime_utc":"2022-04-26T19:00:00Z","tz_time":"2022-04-26T19:00:00.000Z","geo_id":8743,"geo_name":"Baleares"},{"value":397.34,"datetime":"2022-04-26T21:00:00.000+02:00","datetime_utc":"2022-04-26T19:00:00Z","tz_time":"2022-04-26T19:00:00.000Z","geo_id":8744,"geo_name":"Ceuta"},{"value":397.34,"datetime":"2022-04-26T21:00:00.000+02:00","datetime_utc":"2022-04-26T19:00:00Z","tz_time":"2022-04-26T19:00:00.000Z","geo_id":8745,"geo_name":"Melilla"},{"value":338.67,"datetime":"2022-04-26T22:00:00.000+02:00","datetime_utc":"2022-04-26T20:00:00Z","tz_time":"2022-04-26T20:00:00.000Z","geo_id":8741,"geo_name":"Peninsula"},{"value":338.67,"datetime":"2022-04-26T22:00:00.000+02:00","datetime_utc":"2022-04-26T20:00:00Z","tz_time":"2022-04-26T20:00:00.000Z","geo_id":8742,"geo_name":"Canarias"},{"value":338.67,"datetime":"2022-04-26T22:00:00.000+02:00","datetime_utc":"2022-04-26T20:00:00Z","tz_time":"2022-04-26T20:00:00.000Z","geo_id":8743,"geo_name":"Baleares"},{"value":387.37,"datetime":"2022-04-26T22:00:00.000+02:00","datetime_utc":"2022-04-26T20:00:00Z","tz_time":"2022-04-26T20:00:00.000Z","geo_id":8744,"geo_name":"Ceuta"},{"value":387.37,"datetime":"2022-04-26T22:00:00.000+02:00","datetime_utc":"2022-04-26T20:00:00Z","tz_time":"2022-04-26T20:00:00.000Z","geo_id":8745,"geo_name":"Melilla"},{"value":330.48,"datetime":"2022-04-26T23:00:00.000+02:00","datetime_utc":"2022-04-26T21:00:00Z","tz_time":"2022-04-26T21:00:00.000Z","geo_id":8741,"geo_name":"Peninsula"},{"value":330.48,"datetime":"2022-04-26T23:00:00.000+02:00","datetime_utc":"2022-04-26T21:00:00Z","tz_time":"2022-04-26T21:00:00.000Z","geo_id":8742,"geo_name":"Canarias"},{"value":330.48,"datetime":"2022-04-26T23:00:00.000+02:00","datetime_utc":"2022-04-26T21:00:00Z","tz_time":"2022-04-26T21:00:00.000Z","geo_id":8743,"geo_name":"Baleares"},{"value":330.48,"datetime":"2022-04-26T23:00:00.000+02:00","datetime_utc":"2022-04-26T21:00:00Z","tz_time":"2022-04-26T21:00:00.000Z","geo_id":8744,"geo_name":"Ceuta"},{"value":330.48,"datetime":"2022-04-26T23:00:00.000+02:00","datetime_utc":"2022-04-26T21:00:00Z","tz_time":"2022-04-26T21:00:00.000Z","geo_id":8745,"geo_name":"Melilla"}]}}