{"indicator":{"name":"Término de facturación de energía activa del PVPC 2.0TD","short_name":"PVPC T. 2.0TD","id":1001,"composited":false,"step_type":"linear","disaggregated":true,"magnitud":[{"name":"Precio","id":23}],"tiempo":[{"name":"Hora","id":4}],"geos":[{"geo_id":8741,"geo_name":"Península"},{"geo_id":8742,"geo_name":"Canarias"},{"geo_id":8743,"geo_name":"Baleares"},{"geo_id":8744,"geo_name":"Ceuta"},{"geo_id":8745,"geo_name":"Melilla"}],"values_updated_at":"2024-09-10T20:17:44.000+02:00","values":[{"value":119.09,"datetime":"2024-09-11T00:00:00.000+02:00","datetime_utc":"2024-09-10T22:00:00Z","tz_time":"2024-09-10T22:00:00.000Z","geo_id":8741,"geo_name":"Península"},{"value":119.09,"datetime":"2024-09-11T00:00:00.000+02:00","datetime_utc":"2024-09-10T22:00:00Z","tz_time":"2024-09-10T22:00:00.000Z","geo_id":8742,"geo_name":"Canarias"},{"value":119.09,"datetime":"2024-09-11T00:00:00.000+02:00","datetime_utc":"2024-09-10T22:00:00Z","tz_time":"2024-09-10T22:00:00.000Z","geo_id":8743,"geo_name":"Baleares"},{"value":119.09,"datetime":"2024-09-11T00:00:00.000+02:00","datetime_utc":"2024-09-10T22:00:00Z","tz_time":"2024-09-10T22:00:00.000Z","geo_id":8744,"geo_name":"Ceuta"},{"value":119.09,"datetime":"2024-09-11T00:00:00.000+02:00","datetime_utc":"2024-09-10T22:00:00Z","tz_time":"2024-09-10T22:00:00.000Z","geo_id":8745,"geo_name":"Melilla"},{"value":118.73,"datetime":"2024-09-11T01:00:00.000+02:00","datetime_utc":"2024-09-10T23:00:00Z","tz_time":"2024-09-10T23:00:00.000Z","geo_id":8741,"geo_name":"Península"},{"value":118.73,"datetime":"2024-09-11T01:00:00.000+02:00","datetime_utc":"2024-09-10T23:00:00Z","tz_time":"2024-09-10T23:00:00.000Z","geo_id":8742,"geo_name":"Canarias"},{"value":118.73,"datetime":"2024-09-11T01:00:00.000+02:00","datetime_utc":"2024-09-10T23:00:00Z","tz_time":"2024-09-10T23:00:00.000Z","geo_id":8743,"geo_name":"Baleares"},{"value":118.73,"datetime":"2024-09-11T01:00:00.000+02:00","datetime_utc":"2024-09-10T23:00:00Z","tz_time":"2024-09-10T23:00:00.000Z","geo_id":8744,"geo_name":"Ceuta"},{"value":118.73,"datetime":"2024-09-11T01:00:00.000+02:00","datetime_utc":"2024-09-10T23:00:00Z","tz_time":"2024-09-10T23:00:00.000Z","geo_id":8745,"geo_name":"Melilla"},{"value":112.05,"datetime":"2024-09-11T02:00:00.000+02:00","datetime_utc":"2024-09-11T00:00:00Z","tz_time":"2024-09-11T00:00:00.000Z","geo_id":8741,"geo_name":"Península"},{"value":112.05,"datetime":"2024-09-11T02:00:00.000+02:00","datetime_utc":"2024-09-11T00:00:00Z","tz_time":"2024-09-11T00:00:00.000Z","geo_id":8742,"geo_name":"Canarias"},{"value":112.05,"datetime":"2024-09-11T02:00:00.000+02:00","datetime_utc":"2024-09-11T00:00:00Z","tz_time":"2024-09-11T00:00:00.000Z","geo_id":8743,"geo_name":"Baleares"},{"value":112.05,"datetime":"2024-09-11T02:00:00.000+02:00","datetime_utc":"2024-09-11T00:00:00Z","tz_time":"2024-09-11T00:00:00.000Z","geo_id":8744,"geo_name":"Ceuta"},{"value":112.05,"datetime":"2024-09-11T02:00:00.000+02:00","datetime_utc":"2024-09-11T00:00:00Z","tz_time":"2024-09-11T00:00:00.000Z","geo_id":8745,"geo_name":"Melilla"},{"value":124.03,"datetime":"2024-09-11T03:00:00.000+02:00","datetime_utc":"2024-09-11T01:00:00Z","tz_time":"2024-09-11T01:00:00.000Z","geo_id":8741,"geo_name":"Península"},{"value":124.03,"datetime":"2024-09-11T03:00:00.000+02:00","datetime_utc":"2024-09-11T01:00:00Z","tz_time":"2024-09-11T01:00:00.000Z","geo_id":8742,"geo_name":"Canarias"},{"value":124.03,"datetime":"2024-09-11T03:00:00.000+02:00","datetime_utc":"2024-09-11T01:00:00Z","tz_time":"2024-09-11T01:00:00.000Z","geo_id":8743,"geo_name":"Baleares"},{"value":124.03,"datetime":"2024-09-11T03:00:00.000+02:00","datetime_utc":"2024-09-11T01:00:00Z","tz_time":"2024-09-11T01:00:00.000Z","geo_id":8744,"geo_name":"Ceuta"},{"value":124.03,"datetime":"2024-09-11T03:00:00.000+02:00","datetime_utc":"2024-09-11T01:00:00Z","tz_time":"2024-09-11T01:00:00.000Z","geo_id":8745,"geo_name":"Melilla"},{"value":127.96,"datetime":"2024-09-11T04:00:00.000+02:00","datetime_utc":"2024-09-11T02:00:00Z","tz_time":"2024-09-11T02:00:00.000Z","geo_id":8741,"geo_name":"Península"},{"value":127.96,"datetime":"2024-09-11T04:00:00.000+02:00","datetime_utc":"2024-09-11T02:00:00Z","tz_time":"2024-09-11T02:00:00.000Z","geo_id":8742,"geo_name":"Canarias"},{"value":127.96,"datetime":"2024-09-11T04:00:00.000+02:00","datetime_utc":"2024-09-11T02:00:00Z","tz_time":"2024-09-11T02:00:00.000Z","geo_id":8743,"geo_name":"Baleares"},{"value":127.96,"datetime":"2024-09-11T04:00:00.000+02:00","datetime_utc":"2024-09-11T02:00:00Z","tz_time":"2024-09-11T02:00:00.000Z","geo_id":8744,"geo_name":"Ceuta"},{"value":127.96,"datetime":"2024-09-11T04:00:00.000+02:00","datetime_utc":"2024-09-11T02:00:00Z","tz_time":"2024-09-11T02:00:00.000Z","geo_id":8745,"geo_name":"Melilla"},{"value":132.51,"datetime":"2024-09-11T05:00:00.000+02:00","datetime_utc":"2024-09-11T03:00:00Z","tz_time":"2024-09-11T03:00:00.000Z","geo_id":8741,"geo_name":"Península"},{"value":132.51,"datetime":"2024-09-11T05:00:00.000+02:00","datetime_utc":"2024-09-11T03:00:00Z","tz_time":"2024-09-11T03:00:00.000Z","geo_id":8742,"geo_name":"Canarias"},{"value":132.51,"datetime":"2024-09-11T05:00:00.000+02:00","datetime_utc":"2024-09-11T03:00:00Z","tz_time":"2024-09-11T03:00:00.000Z","geo_id":8743,"geo_name":"Baleares"},{"value":132.51,"datetime":"2024-09-11T05:00:00.000+02:00","datetime_utc":"2024-09-11T03:00:00Z","tz_time":"2024-09-11T03:00:00.000Z","geo_id":8744,"geo_name":"Ceuta"},{"value":132.51,"datetime":"2024-09-11T05:00:00.000+02:00","datetime_utc":"2024-09-11T03:00:00Z","tz_time":"2024-09-11T03:00:00.000Z","geo_id":8745,"geo_name":"Melilla"},{"value":136.79,"datetime":"2024-09-11T06:00:00.000+02:00","datetime_utc":"2024-09-11T04:00:00Z","tz_time":"2024-09-11T04:00:00.000Z","geo_id":8741,"geo_name":"Península"},{"value":136.79,"datetime":"2024-09-11T06:00:00.000+02:00","datetime_utc":"2024-09-11T04:00:00Z","tz_time":"2024-09-11T04:00:00.000Z","geo_id":8742,"geo_name":"Canarias"},{"value":136.79,"datetime":"2024-09-11T06:00:00.000+02:00","datetime_utc":"2024-09-11T04:00:00Z","tz_time":"2024-09-11T04:00:00.000Z","geo_id":8743,"geo_name":"Baleares"},{"value":136.79,"datetime":"2024-09-11T06:00:00.000+02:00","datetime_utc":"2024-09-11T04:00:00Z","tz_time":"2024-09-11T04:00:00.000Z","geo_id":8744,"geo_name":"Ceuta"},{"value":136.79,"datetime":"2024-09-11T06:00:00.000+02:00","datetime_utc":"2024-09-11T04:00:00Z","tz_time":"2024-09-11T04:00:00.000Z","geo_id":8745,"geo_name":"Melilla"},{"value":139.13,"datetime":"2024-09-11T07:00:00.000+02:00","datetime_utc":"2024-09-11T05:00:00Z","tz_time":"2024-09-11T05:00:00.000Z","geo_id":8741,"geo_name":"Península"},{"value":139.13,"datetime":"2024-09-11T07:00:00.000+02:00","datetime_utc":"2024-09-11T05:00:00Z","tz_time":"2024-09-11T05:00:00.000Z","geo_id":8742,"geo_name":"Canarias"},{"value":139.13,"datetime":"2024-09-11T07:00:00.000+02:00","datetime_utc":"2024-09-11T05:00:00Z","tz_time":"2024-09-11T05:00:00.000Z","geo_id":8743,"geo_name":"Baleares"},{"value":139.13,"datetime":"2024-09-11T07:00:00.000+02:00","datetime_utc":"2024-09-11T05:00:00Z","tz_time":"2024-09-11T05:00:00.000Z","geo_id":8744,"geo_name":"Ceuta"},{"value":139.13,"datetime":"2024-09-11T07:00:00.000+02:00","datetime_utc":"2024-09-11T05:00:00Z","tz_time":"2024-09-11T05:00:00.000Z","geo_id":8745,"geo_name":"Melilla"},{"value":169.56,"datetime":"2024-09-11T08:00:00.000+02:00","datetime_utc":"2024-09-11T06:00:00Z","tz_time":"2024-09-11T06:00:00.000Z","geo_id":8741,"geo_name":"Península"},{"value":169.56,"datetime":"2024-09-11T08:00:00.000+02:00","datetime_utc":"2024-09-11T06:00:00Z","tz_time":"2024-09-11T06:00:00.000Z","geo_id":8742,"geo_name":"Canarias"},{"value":169.56,"datetime":"2024-09-11T08:00:00.000+02:00","datetime_utc":"2024-09-11T06:00:00Z","tz_time":"2024-09-11T06:00:00.000Z","geo_id":8743,"geo_name":"Baleares"},{"value":169.56,"datetime":"2024-09-11T08:00:00.000+02:00","datetime_utc":"2024-09-11T06:00:00Z","tz_time":"2024-09-11T06:00:00.000Z","geo_id":8744,"geo_name":"Ceuta"},{"value":169.56,"datetime":"2024-09-11T08:00:00.000+02:00","datetime_utc":"2024-09-11T06:00:00Z","tz_time":"2024-09-11T06:00:00.000Z","geo_id":8745,"geo_name":"Melilla"},{"value":158.43,"datetime":"2024-09-11T09:00:00.000+02:00","datetime_utc":"2024-09-11T07:00:00Z","tz_time":"2024-09-11T07:00:00.000Z","geo_id":8741,"geo_name":"Península"},{"value":158.43,"datetime":"2024-09-11T09:00:00.000+02:00","datetime_utc":"2024-09-11T07:00:00Z","tz_time":"2024-09-11T07:00:00.000Z","geo_id":8742,"geo_name":"Canarias"},{"value":158.43,"datetime":"2024-09-11T09:00:00.000+02:00","datetime_utc":"2024-09-11T07:00:00Z","tz_time":"2024-09-11T07:00:00.000Z","geo_id":8743,"geo_name":"Baleares"},{"value":158.43,"datetime":"2024-09-11T09:00:00.000+02:00","datetime_utc":"2024-09-11T07:00:00Z","tz_time":"2024-09-11T07:00:00.000Z","geo_id":8744,"geo_name":"Ceuta"},{"value":158.43,"datetime":"2024-09-11T09:00:00.000+02:00","datetime_utc":"2024-09-11T07:00:00Z","tz_time":"2024-09-11T07:00:00.000Z","geo_id":8745,"geo_name":"Melilla"},{"value":181.47,"datetime":"2024-09-11T10:00:00.000+02:00","datetime_utc":"2024-09-11T08:00:00Z","tz_time":"2024-09-11T08:00:00.000Z","geo_id":8741,"geo_name":"Península"},{"value":181.47,"datetime":"2024-09-11T10:00:00.000+02:00","datetime_utc":"2024-09-11T08:00:00Z","tz_time":"2024-09-11T08:00:00.000Z","geo_id":8742,"geo_name":"Canarias"},{"value":181.47,"datetime":"2024-09-11T10:00:00.000+02:00","datetime_utc":"2024-09-11T08:00:00Z","tz_time":"2024-09-11T08:00:00.000Z","geo_id":8743,"geo_name":"Baleares"},{"value":131.29,"datetime":"2024-09-11T10:00:00.000+02:00","datetime_utc":"2024-09-11T08:00:00Z","tz_time":"2024-09-11T08:00:00.000Z","geo_id":8744,"geo_name":"Ceuta"},{"value":131.29,"datetime":"2024-09-11T10:00:00.000+02:00","datetime_utc":"2024-09-11T08:00:00Z","tz_time":"2024-09-11T08:00:00.000Z","geo_id":8745,"geo_name":"Melilla"},{"value":158.83,"datetime":"2024-09-11T11:00:00.000+02:00","datetime_utc":"2024-09-11T09:00:00Z","tz_time":"2024-09-11T09:00:00.000Z","geo_id":8741,"geo_name":"Península"},{"value":158.83,"datetime":"2024-09-11T11:00:00.000+02:00","datetime_utc":"2024-09-11T09:00:00Z","tz_time":"2024-09-11T09:00:00.000Z","geo_id":8742,"geo_name":"Canarias"},{"value":158.83,"datetime":"2024-09-11T11:00:00.000+02:00","datetime_utc":"2024-09-11T09:00:00Z","tz_time":"2024-09-11T09:00:00.000Z","geo_id":8743,"geo_name":"Baleares"},{"value":158.83,"datetime":"2024-09-11T11:00:00.000+02:00","datetime_utc":"2024-09-11T09:00:00Z","tz_time":"2024-09-11T09:00:00.000Z","geo_id":8744,"geo_name":"Ceuta"},{"value":158.83,"datetime":"2024-09-11T11:00:00.000+02:00","datetime_utc":"2024-09-11T09:00:00Z","tz_time":"2024-09-11T09:00:00.000Z","geo_id":8745,"geo_name":"Melilla"},{"value":156.45,"datetime":"2024-09-11T12:00:00.000+02:00","datetime_utc":"2024-09-11T10:00:00Z","tz_time":"2024-09-11T10:00:00.000Z","geo_id":8741,"geo_name":"Península"},{"value":156.45,"datetime":"2024-09-11T12:00:00.000+02:00","datetime_utc":"2024-09-11T10:00:00Z","tz_time":"2024-09-11T10:00:00.000Z","geo_id":8742,"geo_name":"Canarias"},{"value":156.45,"datetime":"2024-09-11T12:00:00.000+02:00","datetime_utc":"2024-09-11T10:00:00Z","tz_time":"2024-09-11T10:00:00.000Z","geo_id":8743,"geo_name":"Baleares"},{"value":156.45,"datetime":"2024-09-11T12:00:00.000+02:00","datetime_utc":"2024-09-11T10:00:00Z","tz_time":"2024-09-11T10:00:00.000Z","geo_id":8744,"geo_name":"Ceuta"},{"value":156.45,"datetime":"2024-09-11T12:00:00.000+02:00","datetime_utc":"2024-09-11T10:00:00Z","tz_time":"2024-09-11T10:00:00.000Z","geo_id":8745,"geo_name":"Melilla"},{"value":153.05,"datetime":"2024-09-11T13:00:00.000+02:00","datetime_utc":"2024-09-11T11:00:00Z","tz_time":"2024-09-11T11:00:00.000Z","geo_id":8741,"geo_name":"Península"},{"value":153.05,"datetime":"2024-09-11T13:00:00.000+02:00","datetime_utc":"2024-09-11T11:00:00Z","tz_time":"2024-09-11T11:00:00.000Z","geo_id":8742,"geo_name":"Canarias"},{"value":153.05,"datetime":"2024-09-11T13:00:00.000+02:00","datetime_utc":"2024-09-11T11:00:00Z","tz_time":"2024-09-11T11:00:00.000Z","geo_id":8743,"geo_name":"Baleares"},{"value":153.05,"datetime":"2024-09-11T13:00:00.000+02:00","datetime_utc":"2024-09-11T11:00:00Z","tz_time":"2024-09-11T11:00:00.000Z","geo_id":8744,"geo_name":"Ceuta"},{"value":153.05,"datetime":"2024-09-11T13:00:00.000+02:00","datetime_utc":"2024-09-11T11:00:00Z","tz_time":"2024-09-11T11:00:00.000Z","geo_id":8745,"geo_name":"Melilla"},{"value":100.11,"datetime":"2024-09-11T14:00:00.000+02:00","datetime_utc":"2024-09-11T12:00:00Z","tz_time":"2024-09-11T12:00:00.000Z","geo_id":8741,"geo_name":"Península"},{"value":100.11,"datetime":"2024-09-11T14:00:00.000+02:00","datetime_utc":"2024-09-11T12:00:00Z","tz_time":"2024-09-11T12:00:00.000Z","geo_id":8742,"geo_name":"Canarias"},{"value":100.11,"datetime":"2024-09-11T14:00:00.000+02:00","datetime_utc":"2024-09-11T12:00:00Z","tz_time":"2024-09-11T12:00:00.000Z","geo_id":8743,"geo_name":"Baleares"},{"value":150.2,"datetime":"2024-09-11T14:00:00.000+02:00","datetime_utc":"2024-09-11T12:00:00Z","tz_time":"2024-09-11T12:00:00.000Z","geo_id":8744,"geo_name":"Ceuta"},{"value":150.2,"datetime":"2024-09-11T14:00:00.000+02:00","datetime_utc":"2024-09-11T12:00:00Z","tz_time":"2024-09-11T12:00:00.000Z","geo_id":8745,"geo_name":"Melilla"},{"value":76.4,"datetime":"2024-09-11T15:00:00.000+02:00","datetime_utc":"2024-09-11T13:00:00Z","tz_time":"2024-09-11T13:00:00.000Z","geo_id":8741,"geo_name":"Península"},{"value":76.4,"datetime":"2024-09-11T15:00:00.000+02:00","datetime_utc":"2024-09-11T13:00:00Z","tz_time":"2024-09-11T13:00:00.000Z","geo_id":8742,"geo_name":"Canarias"},{"value":76.4,"datetime":"2024-09-11T15:00:00.000+02:00","datetime_utc":"2024-09-11T13:00:00Z","tz_time":"2024-09-11T13:00:00.000Z","geo_id":8743,"geo_name":"Baleares"},{"value":76.4,"datetime":"2024-09-11T15:00:00.000+02:00","datetime_utc":"2024-09-11T13:00:00Z","tz_time":"2024-09-11T13:00:00.000Z","geo_id":8744,"geo_name":"Ceuta"},{"value":76.4,"datetime":"2024-09-11T15:00:00.000+02:00","datetime_utc":"2024-09-11T13:00:00Z","tz_time":"2024-09-11T13:00:00.000Z","geo_id":8745,"geo_name":"Melilla"},{"value":66.57,"datetime":"2024-09-11T16:00:00.000+02:00","datetime_utc":"2024-09-11T14:00:00Z","tz_time":"2024-09-11T14:00:00.000Z","geo_id":8741,"geo_name":"Península"},{"value":66.57,"datetime":"2024-09-11T16:00:00.000+02:00","datetime_utc":"2024-09-11T14:00:00Z","tz_time":"2024-09-11T14:00:00.000Z","geo_id":8742,"geo_name":"Canarias"},{"value":66.57,"datetime":"2024-09-11T16:00:00.000+02:00","datetime_utc":"2024-09-11T14:00:00Z","tz_time":"2024-09-11T14:00:00.000Z","geo_id":8743,"geo_name":"Baleares"},{"value":66.57,"datetime":"2024-09-11T16:00:00.000+02:00","datetime_utc":"2024-09-11T14:00:00Z","tz_time":"2024-09-11T14:00:00.000Z","geo_id":8744,"geo_name":"Ceuta"},{"value":66.57,"datetime":"2024-09-11T16:00:00.000+02:00","datetime_utc":"2024-09-11T14:00:00Z","tz_time":"2024-09-11T14:00:00.000Z","geo_id":8745,"geo_name":"Melilla"},{"value":108.96,"datetime":"2024-09-11T17:00:00.000+02:00","datetime_utc":"2024-09-11T15:00:00Z","tz_time":"2024-09-11T15:00:00.000Z","geo_id":8741,"geo_name":"Península"},{"value":108.96,"datetime":"2024-09-11T17:00:00.000+02:00","datetime_utc":"2024-09-11T15:00:00Z","tz_time":"2024-09-11T15:00:00.000Z","geo_id":8742,"geo_name":"Canarias"},{"value":108.96,"datetime":"2024-09-11T17:00:00.000+02:00","datetime_utc":"2024-09-11T15:00:00Z","tz_time":"2024-09-11T15:00:00.000Z","geo_id":8743,"geo_name":"Baleares"},{"value":108.96,"datetime":"2024-09-11T17:00:00.000+02:00","datetime_utc":"2024-09-11T15:00:00Z","tz_time":"2024-09-11T15:00:00.000Z","geo_id":8744,"geo_name":"Ceuta"},{"value":108.96,"datetime":"2024-09-11T17:00:00.000+02:00","datetime_utc":"2024-09-11T15:00:00Z","tz_time":"2024-09-11T15:00:00.000Z","geo_id":8745,"geo_name":"Melilla"},{"value":190.35,"datetime":"2024-09-11T18:00:00.000+02:00","datetime_utc":"2024-09-11T16:00:00Z","tz_time":"2024-09-11T16:00:00.000Z","geo_id":8741,"geo_name":"Península"},{"value":190.35,"datetime":"2024-09-11T18:00:00.000+02:00","datetime_utc":"2024-09-11T16:00:00Z","tz_time":"2024-09-11T16:00:00.000Z","geo_id":8742,"geo_name":"Canarias"},{"value":190.35,"datetime":"2024-09-11T18:00:00.000+02:00","datetime_utc":"2024-09-11T16:00:00Z","tz_time":"2024-09-11T16:00:00.000Z","geo_id":8743,"geo_name":"Baleares"},{"value":140.04,"datetime":"2024-09-11T18:00:00.000+02:00","datetime_utc":"2024-09-11T16:00:00Z","tz_time":"2024-09-11T16:00:00.000Z","geo_id":8744,"geo_name":"Ceuta"},{"value":140.04,"datetime":"2024-09-11T18:00:00.000+02:00","datetime_utc":"2024-09-11T16:00:00Z","tz_time":"2024-09-11T16:00:00.000Z","geo_id":8745,"geo_name":"Melilla"},{"value":215.65,"datetime":"2024-09-11T19:00:00.000+02:00","datetime_utc":"2024-09-11T17:00:00Z","tz_time":"2024-09-11T17:00:00.000Z","geo_id":8741,"geo_name":"Península"},{"value":215.65,"datetime":"2024-09-11T19:00:00.000+02:00","datetime_utc":"2024-09-11T17:00:00Z","tz_time":"2024-09-11T17:00:00.000Z","geo_id":8742,"geo_name":"Canarias"},{"value":215.65,"datetime":"2024-09-11T19:00:00.000+02:00","datetime_utc":"2024-09-11T17:00:00Z","tz_time":"2024-09-11T17:00:00.000Z","geo_id":8743,"geo_name":"Baleares"},{"value":215.65,"datetime":"2024-09-11T19:00:00.000+02:00","datetime_utc":"2024-09-11T17:00:00Z","tz_time":"2024-09-11T17:00:00.000Z","geo_id":8744,"geo_name":"Ceuta"},{"value":215.65,"datetime":"2024-09-11T19:00:00.000+02:00","datetime_utc":"2024-09-11T17:00:00Z","tz_time":"2024-09-11T17:00:00.000Z","geo_id":8745,"geo_name":"Melilla"},{"value":230.18,"datetime":"2024-09-11T20:00:00.000+02:00","datetime_utc":"2024-09-11T18:00:00Z","tz_time":"2024-09-11T18:00:00.000Z","geo_id":8741,"geo_name":"Península"},{"value":230.18,"datetime":"2024-09-11T20:00:00.000+02:00","datetime_utc":"2024-09-11T18:00:00Z","tz_time":"2024-09-11T18:00:00.000Z","geo_id":8742,"geo_name":"Canarias"},{"value":230.18,"datetime":"2024-09-11T20:00:00.000+02:00","datetime_utc":"2024-09-11T18:00:00Z","tz_time":"2024-09-11T18:00:00.000Z","geo_id":8743,"geo_name":"Baleares"},{"value":230.18,"datetime":"2024-09-11T20:00:00.000+02:00","datetime_utc":"2024-09-11T18:00:00Z","tz_time":"2024-09-11T18:00:00.000Z","geo_id":8744,"geo_name":"Ceuta"},{"value":230.18,"datetime":"2024-09-11T20:00:00.000+02:00","datetime_utc":"2024-09-11T18:00:00Z","tz_time":"2024-09-11T18:00:00.000Z","geo_id":8745,"geo_name":"Melilla"},{"value":227.64,"datetime":"2024-09-11T21:00:00.000+02:00","datetime_utc":"2024-09-11T19:00:00Z","tz_time":"2024-09-11T19:00:00.000Z","geo_id":8741,"geo_name":"Península"},{"value":227.64,"datetime":"2024-09-11T21:00:00.000+02:00","datetime_utc":"2024-09-11T19:00:00Z","tz_time":"2024-09-11T19:00:00.000Z","geo_id":8742,"geo_name":"Canarias"},{"value":227.64,"datetime":"2024-09-11T21:00:00.000+02:00","datetime_utc":"2024-09-11T19:00:00Z","tz_time":"2024-09-11T19:00:00.000Z","geo_id":8743,"geo_name":"Baleares"},{"value":227.64,"datetime":"2024-09-11T21:00:00.000+02:00","datetime_utc":"2024-09-11T19:00:00Z","tz_time":"2024-09-11T19:00:00.000Z","geo_id":8744,"geo_name":"Ceuta"},{"value":227.64,"datetime":"2024-09-11T21:00:00.000+02:00","datetime_utc":"2024-09-11T19:00:00Z","tz_time":"2024-09-11T19:00:00.000Z","geo_id":8745,"geo_name":"Melilla"},{"value":171.65,"datetime":"2024-09-11T22:00:00.000+02:00","datetime_utc":"2024-09-11T20:00:00Z","tz_time":"2024-09-11T20:00:00.000Z","geo_id":8741,"geo_name":"Península"},{"value":171.65,"datetime":"2024-09-11T22:00:00.000+02:00","datetime_utc":"2024-09-11T20:00:00Z","tz_time":"2024-09-11T20:00:00.000Z","geo_id":8742,"geo_name":"Canarias"},{"value":171.65,"datetime":"2024-09-11T22:00:00.000+02:00","datetime_utc":"2024-09-11T20:00:00Z","tz_time":"2024-09-11T20:00:00.000Z","geo_id":8743,"geo_name":"Baleares"},{"value":222.07,"datetime":"2024-09-11T22:00:00.000+02:00","datetime_utc":"2024-09-11T20:00:00Z","tz_time":"2024-09-11T20:00:00.000Z","geo_id":8744,"geo_name":"Ceuta"},{"value":222.07,"datetime":"2024-09-11T22:00:00.000+02:00","datetime_utc":"2024-09-11T20:00:00Z","tz_time":"2024-09-11T20:00:00.000Z","geo_id":8745,"geo_name":"Melilla"},{"value":173.64,"datetime":"2024-09-11T23:00:00.000+02:00","datetime_utc":"2024-09-11T21:00:00Z","tz_time":"2024-09-11T21:00:00.000Z","geo_id":8741,"geo_name":"Península"},{"value":173.64,"datetime":"2024-09-11T23:00:00.000+02:00","datetime_utc":"2024-09-11T21:00:00Z","tz_time":"2024-09-11T21:00:00.000Z","geo_id":8742,"geo_name":"Canarias"},{"value":173.64,"datetime":"2024-09-11T23:00:00.000+02:00","datetime_utc":"2024-09-11T21:00:00Z","tz_time":"2024-09-11T21:00:00.000Z","geo_id":8743,"geo_name":"Baleares"},{"value":173.64,"datetime":"2024-09-11T23:00:00.000+02:00","datetime_utc":"2024-09-11T21:00:00Z","tz_time":"2024-09-11T21:00:00.000Z","geo_id":8744,"geo_name":"Ceuta"},{"value":173.64,"datetime":"2024-09-11T23:00:00.000+02:00","datetime_utc":"2024-09-11T21:00:00Z","tz_time":"2024-09-11T21:00:00.000Z","geo_id":8745,"geo_name":"Melilla"}]}}