{"indicator":{"name":"Término de facturación de energía activa del PVPC 2.0TD","short_name":"PVPC T. 2.0TD","id":1001,"composited":false,"step_type":"linear","disaggregated":true,"magnitud":[{"name":"Precio","id":23}],"tiempo":[{"name":"Hora","id":4}],"geos":[{"geo_id":8741,"geo_name":"Península"},{"geo_id":8742,"geo_name":"Canarias"},{"geo_id":8743,"geo_name":"Baleares"},{"geo_id":8744,"geo_name":"Ceuta"},{"geo_id":8745,"geo_name":"Melilla"}],"values_updated_at":"2024-08-31T20:46:44.000+02:00","values":[{"value":170.47,"datetime":"2024-09-01T00:00:00.000+02:00","datetime_utc":"2024-08-31T22:00:00Z","tz_time":"2024-08-31T22:00:00.000Z","geo_id":8741,"geo_name":"Península"},{"value":170.47,"datetime":"2024-09-01T00:00:00.000+02:00","datetime_utc":"2024-08-31T22:00:00Z","tz_time":"2024-08-31T22:00:00.000Z","geo_id":8742,"geo_name":"Canarias"},{"value":170.47,"datetime":"2024-09-01T00:00:00.000+02:00","datetime_utc":"2024-08-31T22:00:00Z","tz_time":"2024-08-31T22:00:00.000Z","geo_id":8743,"geo_name":"Baleares"},{"value":170.47,"datetime":"2024-09-01T00:00:00.000+02:00","datetime_utc":"2024-08-31T22:00:00Z","tz_time":"2024-08-31T22:00:00.000Z","geo_id":8744,"geo_name":"Ceuta"},{"value":170.47,"datetime":"2024-09-01T00:00:00.000+02:00","datetime_utc":"2024-08-31T22:00:00Z","tz_time":"2024-08-31T22:00:00.000Z","geo_id":8745,"geo_name":"Melilla"},{"value":164.63,"datetime":"2024-09-01T01:00:00.000+02:00","datetime_utc":"2024-08-31T23:00:00Z","tz_time":"2024-08-31T23:00:00.000Z","geo_id":8741,"geo_name":"Península"},{"value":164.63,"datetime":"2024-09-01T01:00:00.000+02:00","datetime_utc":"2024-08-31T23:00:00Z","tz_time":"2024-08-31T23:00:00.000Z","geo_id":8742,"geo_name":"Canarias"},{"value":164.63,"datetime":"2024-09-01T01:00:00.000+02:00","datetime_utc":"2024-08-31T23:00:00Z","tz_time":"2024-08-31T23:00:00.000Z","geo_id":8743,"geo_name":"Baleares"},{"value":164.63,"datetime":"2024-09-01T01:00:00.000+02:00","datetime_utc":"2024-08-31T23:00:00Z","tz_time":"2024-08-31T23:00:00.000Z","geo_id":8744,"geo_name":"Ceuta"},{"value":164.63,"datetime":"2024-09-01T01:00:00.000+02:00","datetime_utc":"2024-08-31T23:00:00Z","tz_time":"2024-08-31T23:00:00.000Z","geo_id":8745,"geo_name":"Melilla"},{"value":161.26,"datetime":"2024-09-01T02:00:00.000+02:00","datetime_utc":"2024-09-01T00:00:00Z","tz_time":"2024-09-01T00:00:00.000Z","geo_id":8741,"geo_name":"Península"},{"value":161.26,"datetime":"2024-09-01T02:00:00.000+02:00","datetime_utc":"2024-09-01T00:00:00Z","tz_time":"2024-09-01T00:00:00.000Z","geo_id":8742,"geo_name":"Canarias"},{"value":161.26,"datetime":"2024-09-01T02:00:00.000+02:00","datetime_utc":"2024-09-01T00:00:00Z","tz_time":"2024-09-01T00:00:00.000Z","geo_id":8743,"geo_name":"Baleares"},{"value":161.26,"datetime":"2024-09-01T02:00:00.000+02:00","datetime_utc":"2024-09-01T00:00:00Z","tz_time":"2024-09-01T00:00:00.000Z","geo_id":8744,"geo_name":"Ceuta"},{"value":161.26,"datetime":"2024-09-01T02:00:00.000+02:00","datetime_utc":"2024-09-01T00:00:00Z","tz_time":"2024-09-01T00:00:00.000Z","geo_id":8745,"geo_name":"Melilla"},{"value":159.97,"datetime":"2024-09-01T03:00:00.000+02:00","datetime_utc":"2024-09-01T01:00:00Z","tz_time":"2024-09-01T01:00:00.000Z","geo_id":8741,"geo_name":"Península"},{"value":159.97,"datetime":"2024-09-01T03:00:00.000+02:00","datetime_utc":"2024-09-01T01:00:00Z","tz_time":"2024-09-01T01:00:00.000Z","geo_id":8742,"geo_name":"Canarias"},{"value":159.97,"datetime":"2024-09-01T03:00:00.000+02:00","datetime_utc":"2024-09-01T01:00:00Z","tz_time":"2024-09-01T01:00:00.000Z","geo_id":8743,"geo_name":"Baleares"},{"value":159.97,"datetime":"2024-09-01T03:00:00.000+02:00","datetime_utc":"2024-09-01T01:00:00Z","tz_time":"2024-09-01T01:00:00.000Z","geo_id":8744,"geo_name":"Ceuta"},{"value":159.97,"datetime":"2024-09-01T03:00:00.000+02:00","datetime_utc":"2024-09-01T01:00:00Z","tz_time":"2024-09-01T01:00:00.000Z","geo_id":8745,"geo_name":"Melilla"},{"value":158.51,"datetime":"2024-09-01T04:00:00.000+02:00","datetime_utc":"2024-09-01T02:00:00Z","tz_time":"2024-09-01T02:00:00.000Z","geo_id":8741,"geo_name":"Península"},{"value":158.51,"datetime":"2024-09-01T04:00:00.000+02:00","datetime_utc":"2024-09-01T02:00:00Z","tz_time":"2024-09-01T02:00:00.000Z","geo_id":8742,"geo_name":"Canarias"},{"value":158.51,"datetime":"2024-09-01T04:00:00.000+02:00","datetime_utc":"2024-09-01T02:00:00Z","tz_time":"2024-09-01T02:00:00.000Z","geo_id":8743,"geo_name":"Baleares"},{"value":158.51,"datetime":"2024-09-01T04:00:00.000+02:00","datetime_utc":"2024-09-01T02:00:00Z","tz_time":"2024-09-01T02:00:00.000Z","geo_id":8744,"geo_name":"Ceuta"},{"value":158.51,"datetime":"2024-09-01T04:00:00.000+02:00","datetime_utc":"2024-09-01T02:00:00Z","tz_time":"2024-09-01T02:00:00.000Z","geo_id":8745,"geo_name":"Melilla"},{"value":156.45,"datetime":"2024-09-01T05:00:00.000+02:00","datetime_utc":"2024-09-01T03:00:00Z","tz_time":"2024-09-01T03:00:00.000Z","geo_id":8741,"geo_name":"Península"},{"value":156.45,"datetime":"2024-09-01T05:00:00.000+02:00","datetime_utc":"2024-09-01T03:00:00Z","tz_time":"2024-09-01T03:00:00.000Z","geo_id":8742,"geo_name":"Canarias"},{"value":156.45,"datetime":"2024-09-01T05:00:00.000+02:00","datetime_utc":"2024-09-01T03:00:00Z","tz_time":"2024-09-01T03:00:00.000Z","geo_id":8743,"geo_name":"Baleares"},{"value":156.45,"datetime":"2024-09-01T05:00:00.000+02:00","datetime_utc":"2024-09-01T03:00:00Z","tz_time":"2024-09-01T03:00:00.000Z","geo_id":8744,"geo_name":"Ceuta"},{"value":156.45,"datetime":"2024-09-01T05:00:00.000+02:00","datetime_utc":"2024-09-01T03:00:00Z","tz_time":"2024-09-01T03:00:00.000Z","geo_id":8745,"geo_name":"Melilla"},{"value":158.52,"datetime":"2024-09-01T06:00:00.000+02:00","datetime_utc":"2024-09-01T04:00:00Z","tz_time":"2024-09-01T04:00:00.000Z","geo_id":8741,"geo_name":"Península"},{"value":158.52,"datetime":"2024-09-01T06:00:00.000+02:00","datetime_utc":"2024-09-01T04:00:00Z","tz_time":"2024-09-01T04:00:00.000Z","geo_id":8742,"geo_name":"Canarias"},{"value":158.52,"datetime":"2024-09-01T06:00:00.000+02:00","datetime_utc":"2024-09-01T04:00:00Z","tz_time":"2024-09-01T04:00:00.000Z","geo_id":8743,"geo_name":"Baleares"},{"value":158.52,"datetime":"2024-09-01T06:00:00.000+02:00","datetime_utc":"2024-09-01T04:00:00Z","tz_time":"2024-09-01T04:00:00.000Z","geo_id":8744,"geo_name":"Ceuta"},{"value":158.52,"datetime":"2024-09-01T06:00:00.000+02:00","datetime_utc":"2024-09-01T04:00:00Z","tz_time":"2024-09-01T04:00:00.000Z","geo_id":8745,"geo_name":"Melilla"},{"value":160.26,"datetime":"2024-09-01T07:00:00.000+02:00","datetime_utc":"2024-09-01T05:00:00Z","tz_time":"2024-09-01T05:00:00.000Z","geo_id":8741,"geo_name":"Península"},{"value":160.26,"datetime":"2024-09-01T07:00:00.000+02:00","datetime_utc":"2024-09-01T05:00:00Z","tz_time":"2024-09-01T05:00:00.000Z","geo_id":8742,"geo_name":"Canarias"},{"value":160.26,"datetime":"2024-09-01T07:00:00.000+02:00","datetime_utc":"2024-09-01T05:00:00Z","tz_time":"2024-09-01T05:00:00.000Z","geo_id":8743,"geo_name":"Baleares"},{"value":160.26,"datetime":"2024-09-01T07:00:00.000+02:00","datetime_utc":"2024-09-01T05:00:00Z","tz_time":"2024-09-01T05:00:00.000Z","geo_id":8744,"geo_name":"Ceuta"},{"value":160.26,"datetime":"2024-09-01T07:00:00.000+02:00","datetime_utc":"2024-09-01T05:00:00Z","tz_time":"2024-09-01T05:00:00.000Z","geo_id":8745,"geo_name":"Melilla"},{"value":153.02,"datetime":"2024-09-01T08:00:00.000+02:00","datetime_utc":"2024-09-01T06:00:00Z","tz_time":"2024-09-01T06:00:00.000Z","geo_id":8741,"geo_name":"Península"},{"value":153.02,"datetime":"2024-09-01T08:00:00.000+02:00","datetime_utc":"2024-09-01T06:00:00Z","tz_time":"2024-09-01T06:00:00.000Z","geo_id":8742,"geo_name":"Canarias"},{"value":153.02,"datetime":"2024-09-01T08:00:00.000+02:00","datetime_utc":"2024-09-01T06:00:00Z","tz_time":"2024-09-01T06:00:00.000Z","geo_id":8743,"geo_name":"Baleares"},{"value":153.02,"datetime":"2024-09-01T08:00:00.000+02:00","datetime_utc":"2024-09-01T06:00:00Z","tz_time":"2024-09-01T06:00:00.000Z","geo_id":8744,"geo_name":"Ceuta"},{"value":153.02,"datetime":"2024-09-01T08:00:00.000+02:00","datetime_utc":"2024-09-01T06:00:00Z","tz_time":"2024-09-01T06:00:00.000Z","geo_id":8745,"geo_name":"Melilla"},{"value":137.26,"datetime":"2024-09-01T09:00:00.000+02:00","datetime_utc":"2024-09-01T07:00:00Z","tz_time":"2024-09-01T07:00:00.000Z","geo_id":8741,"geo_name":"Península"},{"value":137.26,"datetime":"2024-09-01T09:00:00.000+02:00","datetime_utc":"2024-09-01T07:00:00Z","tz_time":"2024-09-01T07:00:00.000Z","geo_id":8742,"geo_name":"Canarias"},{"value":137.26,"datetime":"2024-09-01T09:00:00.000+02:00","datetime_utc":"2024-09-01T07:00:00Z","tz_time":"2024-09-01T07:00:00.000Z","geo_id":8743,"geo_name":"Baleares"},{"value":137.26,"datetime":"2024-09-01T09:00:00.000+02:00","datetime_utc":"2024-09-01T07:00:00Z","tz_time":"2024-09-01T07:00:00.000Z","geo_id":8744,"geo_name":"Ceuta"},{"value":137.26,"datetime":"2024-09-01T09:00:00.000+02:00","datetime_utc":"2024-09-01T07:00:00Z","tz_time":"2024-09-01T07:00:00.000Z","geo_id":8745,"geo_name":"Melilla"},{"value":110.19,"datetime":"2024-09-01T10:00:00.000+02:00","datetime_utc":"2024-09-01T08:00:00Z","tz_time":"2024-09-01T08:00:00.000Z","geo_id":8741,"geo_name":"Península"},{"value":110.19,"datetime":"2024-09-01T10:00:00.000+02:00","datetime_utc":"2024-09-01T08:00:00Z","tz_time":"2024-09-01T08:00:00.000Z","geo_id":8742,"geo_name":"Canarias"},{"value":110.19,"datetime":"2024-09-01T10:00:00.000+02:00","datetime_utc":"2024-09-01T08:00:00Z","tz_time":"2024-09-01T08:00:00.000Z","geo_id":8743,"geo_name":"Baleares"},{"value":110.19,"datetime":"2024-09-01T10:00:00.000+02:00","datetime_utc":"2024-09-01T08:00:00Z","tz_time":"2024-09-01T08:00:00.000Z","geo_id":8744,"geo_name":"Ceuta"},{"value":110.19,"datetime":"2024-09-01T10:00:00.000+02:00","datetime_utc":"2024-09-01T08:00:00Z","tz_time":"2024-09-01T08:00:00.000Z","geo_id":8745,"geo_name":"Melilla"},{"value":76.84,"datetime":"2024-09-01T11:00:00.000+02:00","datetime_utc":"2024-09-01T09:00:00Z","tz_time":"2024-09-01T09:00:00.000Z","geo_id":8741,"geo_name":"Península"},{"value":76.84,"datetime":"2024-09-01T11:00:00.000+02:00","datetime_utc":"2024-09-01T09:00:00Z","tz_time":"2024-09-01T09:00:00.000Z","geo_id":8742,"geo_name":"Canarias"},{"value":76.84,"datetime":"2024-09-01T11:00:00.000+02:00","datetime_utc":"2024-09-01T09:00:00Z","tz_time":"2024-09-01T09:00:00.000Z","geo_id":8743,"geo_name":"Baleares"},{"value":76.84,"datetime":"2024-09-01T11:00:00.000+02:00","datetime_utc":"2024-09-01T09:00:00Z","tz_time":"2024-09-01T09:00:00.000Z","geo_id":8744,"geo_name":"Ceuta"},{"value":76.84,"datetime":"2024-09-01T11:00:00.000+02:00","datetime_utc":"2024-09-01T09:00:00Z","tz_time":"2024-09-01T09:00:00.000Z","geo_id":8745,"geo_name":"Melilla"},{"value":66.68,"datetime":"2024-09-01T12:00:00.000+02:00","datetime_utc":"2024-09-01T10:00:00Z","tz_time":"2024-09-01T10:00:00.000Z","geo_id":8741,"geo_name":"Península"},{"value":66.68,"datetime":"2024-09-01T12:00:00.000+02:00","datetime_utc":"2024-09-01T10:00:00Z","tz_time":"2024-09-01T10:00:00.000Z","geo_id":8742,"geo_name":"Canarias"},{"value":66.68,"datetime":"2024-09-01T12:00:00.000+02:00","datetime_utc":"2024-09-01T10:00:00Z","tz_time":"2024-09-01T10:00:00.000Z","geo_id":8743,"geo_name":"Baleares"},{"value":66.68,"datetime":"2024-09-01T12:00:00.000+02:00","datetime_utc":"2024-09-01T10:00:00Z","tz_time":"2024-09-01T10:00:00.000Z","geo_id":8744,"geo_name":"Ceuta"},{"value":66.68,"datetime":"2024-09-01T12:00:00.000+02:00","datetime_utc":"2024-09-01T10:00:00Z","tz_time":"2024-09-01T10:00:00.000Z","geo_id":8745,"geo_name":"Melilla"},{"value":66.09,"datetime":"2024-09-01T13:00:00.000+02:00","datetime_utc":"2024-09-01T11:00:00Z","tz_time":"2024-09-01T11:00:00.000Z","geo_id":8741,"geo_name":"Península"},{"value":66.09,"datetime":"2024-09-01T13:00:00.000+02:00","datetime_utc":"2024-09-01T11:00:00Z","tz_time":"2024-09-01T11:00:00.000Z","geo_id":8742,"geo_name":"Canarias"},{"value":66.09,"datetime":"2024-09-01T13:00:00.000+02:00","datetime_utc":"2024-09-01T11:00:00Z","tz_time":"2024-09-01T11:00:00.000Z","geo_id":8743,"geo_name":"Baleares"},{"value":66.09,"datetime":"2024-09-01T13:00:00.000+02:00","datetime_utc":"2024-09-01T11:00:00Z","tz_time":"2024-09-01T11:00:00.000Z","geo_id":8744,"geo_name":"Ceuta"},{"value":66.09,"datetime":"2024-09-01T13:00:00.000+02:00","datetime_utc":"2024-09-01T11:00:00Z","tz_time":"2024-09-01T11:00:00.000Z","geo_id":8745,"geo_name":"Melilla"},{"value":70.09,"datetime":"2024-09-01T14:00:00.000+02:00","datetime_utc":"2024-09-01T12:00:00Z","tz_time":"2024-09-01T12:00:00.000Z","geo_id":8741,"geo_name":"Península"},{"value":70.09,"datetime":"2024-09-01T14:00:00.000+02:00","datetime_utc":"2024-09-01T12:00:00Z","tz_time":"2024-09-01T12:00:00.000Z","geo_id":8742,"geo_name":"Canarias"},{"value":70.09,"datetime":"2024-09-01T14:00:00.000+02:00","datetime_utc":"2024-09-01T12:00:00Z","tz_time":"2024-09-01T12:00:00.000Z","geo_id":8743,"geo_name":"Baleares"},{"value":70.09,"datetime":"2024-09-01T14:00:00.000+02:00","datetime_utc":"2024-09-01T12:00:00Z","tz_time":"2024-09-01T12:00:00.000Z","geo_id":8744,"geo_name":"Ceuta"},{"value":70.09,"datetime":"2024-09-01T14:00:00.000+02:00","datetime_utc":"2024-09-01T12:00:00Z","tz_time":"2024-09-01T12:00:00.000Z","geo_id":8745,"geo_name":"Melilla"},{"value":51.62,"datetime":"2024-09-01T15:00:00.000+02:00","datetime_utc":"2024-09-01T13:00:00Z","tz_time":"2024-09-01T13:00:00.000Z","geo_id":8741,"geo_name":"Península"},{"value":51.62,"datetime":"2024-09-01T15:00:00.000+02:00","datetime_utc":"2024-09-01T13:00:00Z","tz_time":"2024-09-01T13:00:00.000Z","geo_id":8742,"geo_name":"Canarias"},{"value":51.62,"datetime":"2024-09-01T15:00:00.000+02:00","datetime_utc":"2024-09-01T13:00:00Z","tz_time":"2024-09-01T13:00:00.000Z","geo_id":8743,"geo_name":"Baleares"},{"value":51.62,"datetime":"2024-09-01T15:00:00.000+02:00","datetime_utc":"2024-09-01T13:00:00Z","tz_time":"2024-09-01T13:00:00.000Z","geo_id":8744,"geo_name":"Ceuta"},{"value":51.62,"datetime":"2024-09-01T15:00:00.000+02:00","datetime_utc":"2024-09-01T13:00:00Z","tz_time":"2024-09-01T13:00:00.000Z","geo_id":8745,"geo_name":"Melilla"},{"value":50.33,"datetime":"2024-09-01T16:00:00.000+02:00","datetime_utc":"2024-09-01T14:00:00Z","tz_time":"2024-09-01T14:00:00.000Z","geo_id":8741,"geo_name":"Península"},{"value":50.33,"datetime":"2024-09-01T16:00:00.000+02:00","datetime_utc":"2024-09-01T14:00:00Z","tz_time":"2024-09-01T14:00:00.000Z","geo_id":8742,"geo_name":"Canarias"},{"value":50.33,"datetime":"2024-09-01T16:00:00.000+02:00","datetime_utc":"2024-09-01T14:00:00Z","tz_time":"2024-09-01T14:00:00.000Z","geo_id":8743,"geo_name":"Baleares"},{"value":50.33,"datetime":"2024-09-01T16:00:00.000+02:00","datetime_utc":"2024-09-01T14:00:00Z","tz_time":"2024-09-01T14:00:00.000Z","geo_id":8744,"geo_name":"Ceuta"},{"value":50.33,"datetime":"2024-09-01T16:00:00.000+02:00","datetime_utc":"2024-09-01T14:00:00Z","tz_time":"2024-09-01T14:00:00.000Z","geo_id":8745,"geo_name":"Melilla"},{"value":110.67,"datetime":"2024-09-01T17:00:00.000+02:00","datetime_utc":"2024-09-01T15:00:00Z","tz_time":"2024-09-01T15:00:00.000Z","geo_id":8741,"geo_name":"Península"},{"value":110.67,"datetime":"2024-09-01T17:00:00.000+02:00","datetime_utc":"2024-09-01T15:00:00Z","tz_time":"2024-09-01T15:00:00.000Z","geo_id":8742,"geo_name":"Canarias"},{"value":110.67,"datetime":"2024-09-01T17:00:00.000+02:00","datetime_utc":"2024-09-01T15:00:00Z","tz_time":"2024-09-01T15:00:00.000Z","geo_id":8743,"geo_name":"Baleares"},{"value":110.67,"datetime":"2024-09-01T17:00:00.000+02:00","datetime_utc":"2024-09-01T15:00:00Z","tz_time":"2024-09-01T15:00:00.000Z","geo_id":8744,"geo_name":"Ceuta"},{"value":110.67,"datetime":"2024-09-01T17:00:00.000+02:00","datetime_utc":"2024-09-01T15:00:00Z","tz_time":"2024-09-01T15:00:00.000Z","geo_id":8745,"geo_name":"Melilla"},{"value":133.96,"datetime":"2024-09-01T18:00:00.000+02:00","datetime_utc":"2024-09-01T16:00:00Z","tz_time":"2024-09-01T16:00:00.000Z","geo_id":8741,"geo_name":"Península"},{"value":133.96,"datetime":"2024-09-01T18:00:00.000+02:00","datetime_utc":"2024-09-01T16:00:00Z","tz_time":"2024-09-01T16:00:00.000Z","geo_id":8742,"geo_name":"Canarias"},{"value":133.96,"datetime":"2024-09-01T18:00:00.000+02:00","datetime_utc":"2024-09-01T16:00:00Z","tz_time":"2024-09-01T16:00:00.000Z","geo_id":8743,"geo_name":"Baleares"},{"value":133.96,"datetime":"2024-09-01T18:00:00.000+02:00","datetime_utc":"2024-09-01T16:00:00Z","tz_time":"2024-09-01T16:00:00.000Z","geo_id":8744,"geo_name":"Ceuta"},{"value":133.96,"datetime":"2024-09-01T18:00:00.000+02:00","datetime_utc":"2024-09-01T16:00:00Z","tz_time":"2024-09-01T16:00:00.000Z","geo_id":8745,"geo_name":"Melilla"},{"value":159.09,"datetime":"2024-09-01T19:00:00.000+02:00","datetime_utc":"2024-09-01T17:00:00Z","tz_time":"2024-09-01T17:00:00.000Z","geo_id":8741,"geo_name":"Península"},{"value":159.09,"datetime":"2024-09-01T19:00:00.000+02:00","datetime_utc":"2024-09-01T17:00:00Z","tz_time":"2024-09-01T17:00:00.000Z","geo_id":8742,"geo_name":"Canarias"},{"value":159.09,"datetime":"2024-09-01T19:00:00.000+02:00","datetime_utc":"2024-09-01T17:00:00Z","tz_time":"2024-09-01T17:00:00.000Z","geo_id":8743,"geo_name":"Baleares"},{"value":159.09,"datetime":"2024-09-01T19:00:00.000+02:00","datetime_utc":"2024-09-01T17:00:00Z","tz_time":"2024-09-01T17:00:00.000Z","geo_id":8744,"geo_name":"Ceuta"},{"value":159.09,"datetime":"2024-09-01T19:00:00.000+02:00","datetime_utc":"2024-09-01T17:00:00Z","tz_time":"2024-09-01T17:00:00.000Z","geo_id":8745,"geo_name":"Melilla"},{"value":171.42,"datetime":"2024-09-01T20:00:00.000+02:00","datetime_utc":"2024-09-01T18:00:00Z","tz_time":"2024-09-01T18:00:00.000Z","geo_id":8741,"geo_name":"Península"},{"value":171.42,"datetime":"2024-09-01T20:00:00.000+02:00","datetime_utc":"2024-09-01T18:00:00Z","tz_time":"2024-09-01T18:00:00.000Z","geo_id":8742,"geo_name":"Canarias"},{"value":171.42,"datetime":"2024-09-01T20:00:00.000+02:00","datetime_utc":"2024-09-01T18:00:00Z","tz_time":"2024-09-01T18:00:00.000Z","geo_id":8743,"geo_name":"Baleares"},{"value":171.42,"datetime":"2024-09-01T20:00:00.000+02:00","datetime_utc":"2024-09-01T18:00:00Z","tz_time":"2024-09-01T18:00:00.000Z","geo_id":8744,"geo_name":"Ceuta"},{"value":171.42,"datetime":"2024-09-01T20:00:00.000+02:00","datetime_utc":"2024-09-01T18:00:00Z","tz_time":"2024-09-01T18:00:00.000Z","geo_id":8745,"geo_name":"Melilla"},{"value":181.53,"datetime":"2024-09-01T21:00:00.000+02:00","datetime_utc":"2024-09-01T19:00:00Z","tz_time":"2024-09-01T19:00:00.000Z","geo_id":8741,"geo_name":"Península"},{"value":181.53,"datetime":"2024-09-01T21:00:00.000+02:00","datetime_utc":"2024-09-01T19:00:00Z","tz_time":"2024-09-01T19:00:00.000Z","geo_id":8742,"geo_name":"Canarias"},{"value":181.53,"datetime":"2024-09-01T21:00:00.000+02:00","datetime_utc":"2024-09-01T19:00:00Z","tz_time":"2024-09-01T19:00:00.000Z","geo_id":8743,"geo_name":"Baleares"},{"value":181.53,"datetime":"2024-09-01T21:00:00.000+02:00","datetime_utc":"2024-09-01T19:00:00Z","tz_time":"2024-09-01T19:00:00.000Z","geo_id":8744,"geo_name":"Ceuta"},{"value":181.53,"datetime":"2024-09-01T21:00:00.000+02:00","datetime_utc":"2024-09-01T19:00:00Z","tz_time":"2024-09-01T19:00:00.000Z","geo_id":8745,"geo_name":"Melilla"},{"value":179.96,"datetime":"2024-09-01T22:00:00.000+02:00","datetime_utc":"2024-09-01T20:00:00Z","tz_time":"2024-09-01T20:00:00.000Z","geo_id":8741,"geo_name":"Península"},{"value":179.96,"datetime":"2024-09-01T22:00:00.000+02:00","datetime_utc":"2024-09-01T20:00:00Z","tz_time":"2024-09-01T20:00:00.000Z","geo_id":8742,"geo_name":"Canarias"},{"value":179.96,"datetime":"2024-09-01T22:00:00.000+02:00","datetime_utc":"2024-09-01T20:00:00Z","tz_time":"2024-09-01T20:00:00.000Z","geo_id":8743,"geo_name":"Baleares"},{"value":179.96,"datetime":"2024-09-01T22:00:00.000+02:00","datetime_utc":"2024-09-01T20:00:00Z","tz_time":"2024-09-01T20:00:00.000Z","geo_id":8744,"geo_name":"Ceuta"},{"value":179.96,"datetime":"2024-09-01T22:00:00.000+02:00","datetime_utc":"2024-09-01T20:00:00Z","tz_time":"2024-09-01T20:00:00.000Z","geo_id":8745,"geo_name":"Melilla"},{"value":168.63,"datetime":"2024-09-01T23:00:00.000+02:00","datetime_utc":"2024-09-01T21:00:00Z","tz_time":"2024-09-01T21:00:00.000Z","geo_id":8741,"geo_name":"Península"},{"value":168.63,"datetime":"2024-09-01T23:00:00.000+02:00","datetime_utc":"2024-09-01T21:00:00Z","tz_time":"2024-09-01T21:00:00.000Z","geo_id":8742,"geo_name":"Canarias"},{"value":168.63,"datetime":"2024-09-01T23:00:00.000+02:00","datetime_utc":"2024-09-01T21:00:00Z","tz_time":"2024-09-01T21:00:00.000Z","geo_id":8743,"geo_name":"Baleares"},{"value":168.63,"datetime":"2024-09-01T23:00:00.000+02:00","datetime_utc":"2024-09-01T21:00:00Z","tz_time":"2024-09-01T21:00:00.000Z","geo_id":8744,"geo_name":"Ceuta"},{"value":168.63,"datetime":"2024-09-01T23:00:00.000+02:00","datetime_utc":"2024-09-01T21:00:00Z","tz_time":"2024-09-01T21:00:00.000Z","geo_id":8745,"geo_name":"Melilla"}]}}